{
"type": "FeatureCollection",
"crs": { "type": "name", "properties": { "name": "urn:ogc:def:crs:OGC:1.3:CRS84" } },
"features": [
{ "type": "Feature", "properties": { "city_and_state": "Aberdeen, SD", "black_pop_pct_chg_1940_1970": -0.005, "black_pop_pct_chg_1910_1940": 0.0, "city": "Aberdeen", "state": "SD", "state_fips": "46", "GISJOIN": "G46000100", "state_full": "South Dakota", "place": "Aberdeen city" }, "geometry": { "type": "Point", "coordinates": [ -98.486482900063052, 45.464698500239102 ] } },
{ "type": "Feature", "properties": { "city_and_state": "Abilene, TX", "black_pop_pct_chg_1940_1970": -0.008, "black_pop_pct_chg_1910_1940": 0.001, "city": "Abilene", "state": "TX", "state_fips": "48", "GISJOIN": "G48001000", "state_full": "Texas", "place": "Abilene city" }, "geometry": { "type": "Point", "coordinates": [ -99.733143899614333, 32.448736399876481 ] } },
{ "type": "Feature", "properties": { "city_and_state": "Akron, OH", "black_pop_pct_chg_1940_1970": 0.041, "black_pop_pct_chg_1910_1940": 0.125, "city": "Akron", "state": "OH", "state_fips": "39", "GISJOIN": "G39001000", "state_full": "Ohio", "place": "Akron city" }, "geometry": { "type": "Point", "coordinates": [ -81.519005299799076, 41.08144469990571 ] } },
{ "type": "Feature", "properties": { "city_and_state": "Albany, NY", "black_pop_pct_chg_1940_1970": 0.012, "black_pop_pct_chg_1910_1940": 0.1, "city": "Albany", "state": "NY", "state_fips": "36", "GISJOIN": "G36001000", "state_full": "New York", "place": "Albany city" }, "geometry": { "type": "Point", "coordinates": [ -73.756231700009039, 42.652579300165456 ] } },
{ "type": "Feature", "properties": { "city_and_state": "Albuquerque, NM", "black_pop_pct_chg_1940_1970": -0.007, "black_pop_pct_chg_1910_1940": 0.007, "city": "Albuquerque", "state": "NM", "state_fips": "35", "GISJOIN": "G35002000", "state_full": "New Mexico", "place": "Albuquerque city" }, "geometry": { "type": "Point", "coordinates": [ -106.651136700307106, 35.084490900051961 ] } },
{ "type": "Feature", "properties": { "city_and_state": "Alexandria, VA", "black_pop_pct_chg_1940_1970": -0.116, "black_pop_pct_chg_1910_1940": -0.017, "city": "Alexandria", "state": "VA", "state_fips": "51", "GISJOIN": "G51001000", "state_full": "Virginia", "place": "Alexandria city" }, "geometry": { "type": "Point", "coordinates": [ -77.046921399509827, 38.804835600274352 ] } },
{ "type": "Feature", "properties": { "city_and_state": "Allentown, PA", "black_pop_pct_chg_1940_1970": 0.001, "black_pop_pct_chg_1910_1940": 0.014, "city": "Allentown", "state": "PA", "state_fips": "42", "GISJOIN": "G42002000", "state_full": "Pennsylvania", "place": "Allentown city" }, "geometry": { "type": "Point", "coordinates": [ -75.49018329988678, 40.608430499955077 ] } },
{ "type": "Feature", "properties": { "city_and_state": "Amarillo, TX", "black_pop_pct_chg_1940_1970": 0.041, "black_pop_pct_chg_1910_1940": -0.001, "city": "Amarillo", "state": "TX", "state_fips": "48", "GISJOIN": "G48003000", "state_full": "Texas", "place": "Amarillo city" }, "geometry": { "type": "Point", "coordinates": [ -101.83129689995306, 35.221997099922667 ] } },
{ "type": "Feature", "properties": { "city_and_state": "Anaheim, CA", "black_pop_pct_chg_1940_1970": null, "black_pop_pct_chg_1910_1940": 0.0, "city": "Anaheim", "state": "CA", "state_fips": "06", "GISJOIN": "G06002000", "state_full": "California", "place": "Anaheim city" }, "geometry": { "type": "Point", "coordinates": [ -117.91450359988842, 33.835293199790968 ] } },
{ "type": "Feature", "properties": { "city_and_state": null, "black_pop_pct_chg_1940_1970": null, "black_pop_pct_chg_1910_1940": null, "city": null, "state": null, "state_fips": null, "GISJOIN": null, "state_full": null, "place": null }, "geometry": null },
{ "type": "Feature", "properties": { "city_and_state": "Ann Arbor, MI", "black_pop_pct_chg_1940_1970": 0.006, "black_pop_pct_chg_1910_1940": 0.026, "city": "Ann Arbor", "state": "MI", "state_fips": "26", "GISJOIN": "G26003000", "state_full": "Michigan", "place": "Ann Arbor city" }, "geometry": { "type": "Point", "coordinates": [ -83.726329400078697, 42.270871599987466 ] } },
{ "type": "Feature", "properties": { "city_and_state": "Astoria, OR", "black_pop_pct_chg_1940_1970": -0.002, "black_pop_pct_chg_1910_1940": 0.005, "city": "Astoria", "state": "OR", "state_fips": "41", "GISJOIN": "G41003150", "state_full": "Oregon", "place": "Astoria city" }, "geometry": { "type": "Point", "coordinates": [ -123.831253399323913, 46.187884099869315 ] } },
{ "type": "Feature", "properties": { "city_and_state": "Atlanta, GA", "black_pop_pct_chg_1940_1970": 0.011, "black_pop_pct_chg_1910_1940": 0.167, "city": "Atlanta", "state": "GA", "state_fips": "13", "GISJOIN": "G13004000", "state_full": "Georgia", "place": "Atlanta city" }, "geometry": { "type": "Point", "coordinates": [ -84.387982399654135, 33.748995400203398 ] } },
{ "type": "Feature", "properties": { "city_and_state": "Augusta, GA", "black_pop_pct_chg_1940_1970": -0.037, "black_pop_pct_chg_1910_1940": 0.089, "city": "Augusta", "state": "GA", "state_fips": "13", "GISJOIN": null, "state_full": null, "place": null }, "geometry": null },
{ "type": "Feature", "properties": { "city_and_state": "Aurora, CO", "black_pop_pct_chg_1940_1970": null, "black_pop_pct_chg_1910_1940": 0.01, "city": "Aurora", "state": "CO", "state_fips": "08", "GISJOIN": "G08004000", "state_full": "Colorado", "place": "Aurora city" }, "geometry": { "type": "Point", "coordinates": [ -104.831919499936845, 39.729431899632509 ] } },
{ "type": "Feature", "properties": { "city_and_state": "Austin, TX", "black_pop_pct_chg_1940_1970": -0.081, "black_pop_pct_chg_1910_1940": -0.051, "city": "Austin", "state": "TX", "state_fips": "48", "GISJOIN": "G48005000", "state_full": "Texas", "place": "Austin city" }, "geometry": { "type": "Point", "coordinates": [ -97.743060800351017, 30.267153000249184 ] } },
{ "type": "Feature", "properties": { "city_and_state": "Bakersfield, CA", "black_pop_pct_chg_1940_1970": 0.014, "black_pop_pct_chg_1910_1940": 0.098, "city": "Bakersfield", "state": "CA", "state_fips": "06", "GISJOIN": "G06003526", "state_full": "California", "place": "Bakersfield city" }, "geometry": { "type": "Point", "coordinates": [ -119.01871249972038, 35.373292100060574 ] } },
{ "type": "Feature", "properties": { "city_and_state": "Baltimore, MD", "black_pop_pct_chg_1940_1970": 0.041, "black_pop_pct_chg_1910_1940": 0.271, "city": "Baltimore", "state": "MD", "state_fips": "24", "GISJOIN": "G24004000", "state_full": "Maryland", "place": "Baltimore city" }, "geometry": { "type": "Point", "coordinates": [ -76.612189300128392, 39.290384800390193 ] } },
{ "type": "Feature", "properties": { "city_and_state": "Bangor, ME", "black_pop_pct_chg_1940_1970": -0.001, "black_pop_pct_chg_1910_1940": 0.002, "city": "Bangor", "state": "ME", "state_fips": "23", "GISJOIN": "G23002795", "state_full": "Maine", "place": "Bangor city" }, "geometry": { "type": "Point", "coordinates": [ -68.777813799472469, 44.801182099714048 ] } },
{ "type": "Feature", "properties": { "city_and_state": "Barre, VT", "black_pop_pct_chg_1940_1970": 0.0, "black_pop_pct_chg_1910_1940": 0.0, "city": "Barre", "state": "VT", "state_fips": "50", "GISJOIN": "G50003175", "state_full": "Vermont", "place": "Barre city" }, "geometry": { "type": "Point", "coordinates": [ -72.502049399523273, 44.197005500047517 ] } },
{ "type": "Feature", "properties": { "city_and_state": "Baton Rouge, LA", "black_pop_pct_chg_1940_1970": -0.195, "black_pop_pct_chg_1910_1940": -0.056, "city": "Baton Rouge", "state": "LA", "state_fips": "22", "GISJOIN": "G22005000", "state_full": "Louisiana", "place": "Baton Rouge city" }, "geometry": { "type": "Point", "coordinates": [ -91.154550999901076, 30.450746200021953 ] } },
{ "type": "Feature", "properties": { "city_and_state": "Beaumont, TX", "black_pop_pct_chg_1940_1970": -0.014, "black_pop_pct_chg_1910_1940": -0.014, "city": "Beaumont", "state": "TX", "state_fips": "48", "GISJOIN": "G48007000", "state_full": "Texas", "place": "Beaumont city" }, "geometry": { "type": "Point", "coordinates": [ -94.101846100359822, 30.086045899852547 ] } },
{ "type": "Feature", "properties": { "city_and_state": "Berkeley, CA", "black_pop_pct_chg_1940_1970": 0.034, "black_pop_pct_chg_1910_1940": 0.195, "city": "Berkeley", "state": "CA", "state_fips": "06", "GISJOIN": "G06006000", "state_full": "California", "place": "Berkeley city" }, "geometry": { "type": "Point", "coordinates": [ -122.272746999900761, 37.87159260028686 ] } },
{ "type": "Feature", "properties": { "city_and_state": "Billings, MT", "black_pop_pct_chg_1940_1970": -0.008, "black_pop_pct_chg_1910_1940": -0.003, "city": "Billings", "state": "MT", "state_fips": "30", "GISJOIN": "G30006550", "state_full": "Montana", "place": "Billings city" }, "geometry": { "type": "Point", "coordinates": [ -108.500690399574822, 45.783285599955043 ] } },
{ "type": "Feature", "properties": { "city_and_state": "Biloxi, MS", "black_pop_pct_chg_1940_1970": -0.031, "black_pop_pct_chg_1910_1940": -0.012, "city": "Biloxi", "state": "MS", "state_fips": "28", "GISJOIN": "G28006220", "state_full": "Mississippi", "place": "Biloxi city" }, "geometry": { "type": "Point", "coordinates": [ -88.885307799894861, 30.396031799601058 ] } },
{ "type": "Feature", "properties": { "city_and_state": "Birmingham, AL", "black_pop_pct_chg_1940_1970": 0.013, "black_pop_pct_chg_1910_1940": 0.013, "city": "Birmingham", "state": "AL", "state_fips": "01", "GISJOIN": "G01007000", "state_full": "Alabama", "place": "Birmingham city" }, "geometry": { "type": "Point", "coordinates": [ -86.802489999464555, 33.520660800291417 ] } },
{ "type": "Feature", "properties": { "city_and_state": "Boise, ID", "black_pop_pct_chg_1940_1970": -0.004, "black_pop_pct_chg_1910_1940": 0.0, "city": "Boise", "state": "ID", "state_fips": "16", "GISJOIN": null, "state_full": null, "place": null }, "geometry": null },
{ "type": "Feature", "properties": { "city_and_state": "Boston, MA", "black_pop_pct_chg_1940_1970": 0.01, "black_pop_pct_chg_1910_1940": 0.133, "city": "Boston", "state": "MA", "state_fips": "25", "GISJOIN": "G25007000", "state_full": "Massachusetts", "place": "Boston city" }, "geometry": { "type": "Point", "coordinates": [ -71.059773199348541, 42.358430800104323 ] } },
{ "type": "Feature", "properties": { "city_and_state": "Bridgeport, CT", "black_pop_pct_chg_1940_1970": 0.013, "black_pop_pct_chg_1910_1940": 0.138, "city": "Bridgeport", "state": "CT", "state_fips": "09", "GISJOIN": "G09008000", "state_full": "Connecticut", "place": "Bridgeport city" }, "geometry": { "type": "Point", "coordinates": [ -73.204834800509204, 41.167041200070656 ] } },
{ "type": "Feature", "properties": { "city_and_state": "Buffalo, NY", "black_pop_pct_chg_1940_1970": 0.027, "black_pop_pct_chg_1910_1940": 0.173, "city": "Buffalo", "state": "NY", "state_fips": "36", "GISJOIN": "G36011000", "state_full": "New York", "place": "Buffalo city" }, "geometry": { "type": "Point", "coordinates": [ -78.878368900340035, 42.88644680019668 ] } },
{ "type": "Feature", "properties": { "city_and_state": "Burlington, VT", "black_pop_pct_chg_1940_1970": -0.003, "black_pop_pct_chg_1910_1940": 0.001, "city": "Burlington", "state": "VT", "state_fips": "50", "GISJOIN": "G50010675", "state_full": "Vermont", "place": "Burlington city" }, "geometry": { "type": "Point", "coordinates": [ -73.212071999779795, 44.475882499679166 ] } },
{ "type": "Feature", "properties": { "city_and_state": "Butte, MT", "black_pop_pct_chg_1940_1970": -0.002, "black_pop_pct_chg_1910_1940": -0.003, "city": "Butte", "state": "MT", "state_fips": "30", "GISJOIN": null, "state_full": null, "place": null }, "geometry": null },
{ "type": "Feature", "properties": { "city_and_state": "Cambridge, MA", "black_pop_pct_chg_1940_1970": -0.001, "black_pop_pct_chg_1910_1940": 0.024, "city": "Cambridge", "state": "MA", "state_fips": "25", "GISJOIN": "G25011000", "state_full": "Massachusetts", "place": "Cambridge city" }, "geometry": { "type": "Point", "coordinates": [ -71.105607900383703, 42.375096999678441 ] } },
{ "type": "Feature", "properties": { "city_and_state": "Camden, NJ", "black_pop_pct_chg_1940_1970": 0.042, "black_pop_pct_chg_1910_1940": 0.285, "city": "Camden", "state": "NJ", "state_fips": "34", "GISJOIN": "G34010000", "state_full": "New Jersey", "place": "Camden city" }, "geometry": { "type": "Point", "coordinates": [ -75.119619900274969, 39.92594630036961 ] } },
{ "type": "Feature", "properties": { "city_and_state": "Canton, OH", "black_pop_pct_chg_1940_1970": 0.031, "black_pop_pct_chg_1910_1940": 0.088, "city": "Canton", "state": "OH", "state_fips": "39", "GISJOIN": "G39012000", "state_full": "Ohio", "place": "Canton city" }, "geometry": { "type": "Point", "coordinates": [ -81.378446999842794, 40.798947300250781 ] } },
{ "type": "Feature", "properties": { "city_and_state": "Casper, WY", "black_pop_pct_chg_1940_1970": 0.002, "black_pop_pct_chg_1910_1940": 0.002, "city": "Casper", "state": "WY", "state_fips": "56", "GISJOIN": "G56013150", "state_full": "Wyoming", "place": "Casper city" }, "geometry": { "type": "Point", "coordinates": [ -106.313081000547385, 42.866631999525396 ] } },
{ "type": "Feature", "properties": { "city_and_state": "Cedar Rapids, IA", "black_pop_pct_chg_1940_1970": 0.004, "black_pop_pct_chg_1910_1940": 0.005, "city": "Cedar Rapids", "state": "IA", "state_fips": "19", "GISJOIN": "G19012000", "state_full": "Iowa", "place": "Cedar Rapids city" }, "geometry": { "type": "Point", "coordinates": [ -91.644068300472071, 42.008332799978334 ] } },
{ "type": "Feature", "properties": { "city_and_state": "Charleston, SC", "black_pop_pct_chg_1940_1970": -0.082, "black_pop_pct_chg_1910_1940": 0.006, "city": "Charleston", "state": "SC", "state_fips": "45", "GISJOIN": "G45013330", "state_full": "South Carolina", "place": "Charleston city" }, "geometry": { "type": "Point", "coordinates": [ -79.930921600401717, 32.776565599775019 ] } },
{ "type": "Feature", "properties": { "city_and_state": "Charleston, WV", "black_pop_pct_chg_1940_1970": -0.031, "black_pop_pct_chg_1910_1940": 0.0, "city": "Charleston", "state": "WV", "state_fips": "54", "GISJOIN": "G54014600", "state_full": "West Virginia", "place": "Charleston city" }, "geometry": { "type": "Point", "coordinates": [ -81.632623500222124, 38.349819500465436 ] } },
{ "type": "Feature", "properties": { "city_and_state": "Charlotte, NC", "black_pop_pct_chg_1940_1970": -0.034, "black_pop_pct_chg_1910_1940": -0.009, "city": "Charlotte", "state": "NC", "state_fips": "37", "GISJOIN": "G37012000", "state_full": "North Carolina", "place": "Charlotte city" }, "geometry": { "type": "Point", "coordinates": [ -80.843126800549527, 35.227086899912628 ] } },
{ "type": "Feature", "properties": { "city_and_state": "Chattanooga, TN", "black_pop_pct_chg_1940_1970": -0.118, "black_pop_pct_chg_1910_1940": 0.074, "city": "Chattanooga", "state": "TN", "state_fips": "47", "GISJOIN": "G47014000", "state_full": "Tennessee", "place": "Chattanooga city" }, "geometry": { "type": "Point", "coordinates": [ -85.309680099605316, 35.045629699691489 ] } },
{ "type": "Feature", "properties": { "city_and_state": "Cheyenne, WY", "black_pop_pct_chg_1940_1970": -0.046, "black_pop_pct_chg_1910_1940": 0.013, "city": "Cheyenne", "state": "WY", "state_fips": "56", "GISJOIN": "G56013900", "state_full": "Wyoming", "place": "Cheyenne city" }, "geometry": { "type": "Point", "coordinates": [ -104.82024620041976, 41.139981399968654 ] } },
{ "type": "Feature", "properties": { "city_and_state": "Chicago, IL", "black_pop_pct_chg_1940_1970": 0.062, "black_pop_pct_chg_1910_1940": 0.246, "city": "Chicago", "state": "IL", "state_fips": "17", "GISJOIN": "G17014000", "state_full": "Illinois", "place": "Chicago city" }, "geometry": { "type": "Point", "coordinates": [ -87.650052300382299, 41.850033000440817 ] } },
{ "type": "Feature", "properties": { "city_and_state": "Cincinnati, OH", "black_pop_pct_chg_1940_1970": 0.068, "black_pop_pct_chg_1910_1940": 0.154, "city": "Cincinnati", "state": "OH", "state_fips": "39", "GISJOIN": "G39015000", "state_full": "Ohio", "place": "Cincinnati city" }, "geometry": { "type": "Point", "coordinates": [ -84.45688630015772, 39.162003600007729 ] } },
{ "type": "Feature", "properties": { "city_and_state": "Cleveland, OH", "black_pop_pct_chg_1940_1970": 0.081, "black_pop_pct_chg_1910_1940": 0.287, "city": "Cleveland", "state": "OH", "state_fips": "39", "GISJOIN": "G39016000", "state_full": "Ohio", "place": "Cleveland city" }, "geometry": { "type": "Point", "coordinates": [ -81.695408800585014, 41.499495400001017 ] } },
{ "type": "Feature", "properties": { "city_and_state": "Colorado Springs, CO", "black_pop_pct_chg_1940_1970": -0.009, "black_pop_pct_chg_1910_1940": 0.023, "city": "Colorado Springs", "state": "CO", "state_fips": "08", "GISJOIN": "G08016000", "state_full": "Colorado", "place": "Colorado Springs city" }, "geometry": { "type": "Point", "coordinates": [ -104.821363400571173, 38.833881600305574 ] } },
{ "type": "Feature", "properties": { "city_and_state": "Columbia, SC", "black_pop_pct_chg_1940_1970": -0.083, "black_pop_pct_chg_1910_1940": -0.056, "city": "Columbia", "state": "SC", "state_fips": "45", "GISJOIN": "G45016000", "state_full": "South Carolina", "place": "Columbia city" }, "geometry": { "type": "Point", "coordinates": [ -81.034814399893207, 34.00071040014469 ] } },
{ "type": "Feature", "properties": { "city_and_state": "Columbus, GA", "black_pop_pct_chg_1940_1970": -0.044, "black_pop_pct_chg_1910_1940": -0.065, "city": "Columbus", "state": "GA", "state_fips": "13", "GISJOIN": "G13019000", "state_full": "Georgia", "place": "Columbus city" }, "geometry": { "type": "Point", "coordinates": [ -84.98770939971628, 32.460976399774161 ] } },
{ "type": "Feature", "properties": { "city_and_state": "Columbus, OH", "black_pop_pct_chg_1940_1970": 0.047, "black_pop_pct_chg_1910_1940": 0.068, "city": "Columbus", "state": "OH", "state_fips": "39", "GISJOIN": "G39018000", "state_full": "Ohio", "place": "Columbus city" }, "geometry": { "type": "Point", "coordinates": [ -82.998794200203406, 39.961175499798976 ] } },
{ "type": "Feature", "properties": { "city_and_state": "Concord, NH", "black_pop_pct_chg_1940_1970": -0.001, "black_pop_pct_chg_1910_1940": 0.0, "city": "Concord", "state": "NH", "state_fips": "33", "GISJOIN": "G33014200", "state_full": "New Hampshire", "place": "Concord city" }, "geometry": { "type": "Point", "coordinates": [ -71.537571800297158, 43.208136599895305 ] } },
{ "type": "Feature", "properties": { "city_and_state": "Corpus Christi, TX", "black_pop_pct_chg_1940_1970": 0.026, "black_pop_pct_chg_1910_1940": -0.028, "city": "Corpus Christi", "state": "TX", "state_fips": "48", "GISJOIN": "G48017000", "state_full": "Texas", "place": "Corpus Christi city" }, "geometry": { "type": "Point", "coordinates": [ -97.396380999673383, 27.800582799827311 ] } },
{ "type": "Feature", "properties": { "city_and_state": "Covington, KY", "black_pop_pct_chg_1940_1970": -0.004, "black_pop_pct_chg_1910_1940": 0.013, "city": "Covington", "state": "KY", "state_fips": "21", "GISJOIN": "G21017848", "state_full": "Kentucky", "place": "Covington city" }, "geometry": { "type": "Point", "coordinates": [ -84.508553699950511, 39.083671199581126 ] } },
{ "type": "Feature", "properties": { "city_and_state": "Cumberland, MD", "black_pop_pct_chg_1940_1970": -0.021, "black_pop_pct_chg_1910_1940": 0.001, "city": "Cumberland", "state": "MD", "state_fips": "24", "GISJOIN": "G24021325", "state_full": "Maryland", "place": "Cumberland city" }, "geometry": { "type": "Point", "coordinates": [ -78.762518500204678, 39.652865399785298 ] } },
{ "type": "Feature", "properties": { "city_and_state": "Dallas, TX", "black_pop_pct_chg_1940_1970": -0.025, "black_pop_pct_chg_1910_1940": 0.078, "city": "Dallas", "state": "TX", "state_fips": "48", "GISJOIN": "G48019000", "state_full": "Texas", "place": "Dallas city" }, "geometry": { "type": "Point", "coordinates": [ -96.80666670048609, 32.783055600052634 ] } },
{ "type": "Feature", "properties": { "city_and_state": "Davenport, IA", "black_pop_pct_chg_1940_1970": -0.001, "black_pop_pct_chg_1910_1940": 0.029, "city": "Davenport", "state": "IA", "state_fips": "19", "GISJOIN": "G19019000", "state_full": "Iowa", "place": "Davenport city" }, "geometry": { "type": "Point", "coordinates": [ -90.577636700489663, 41.523643699704138 ] } },
{ "type": "Feature", "properties": { "city_and_state": "Dayton, OH", "black_pop_pct_chg_1940_1970": 0.055, "black_pop_pct_chg_1910_1940": 0.209, "city": "Dayton", "state": "OH", "state_fips": "39", "GISJOIN": "G39021000", "state_full": "Ohio", "place": "Dayton city" }, "geometry": { "type": "Point", "coordinates": [ -84.191606899718067, 39.758947799802407 ] } },
{ "type": "Feature", "properties": { "city_and_state": "Denver, CO", "black_pop_pct_chg_1940_1970": -0.001, "black_pop_pct_chg_1910_1940": 0.067, "city": "Denver", "state": "CO", "state_fips": "08", "GISJOIN": "G08020000", "state_full": "Colorado", "place": "Denver city" }, "geometry": { "type": "Point", "coordinates": [ -104.984703399711705, 39.739153599656937 ] } },
{ "type": "Feature", "properties": { "city_and_state": "Des Moines, IA", "black_pop_pct_chg_1940_1970": 0.006, "black_pop_pct_chg_1910_1940": 0.017, "city": "Des Moines", "state": "IA", "state_fips": "19", "GISJOIN": "G19021000", "state_full": "Iowa", "place": "Des Moines city" }, "geometry": { "type": "Point", "coordinates": [ -93.609106400056547, 41.600544800036069 ] } },
{ "type": "Feature", "properties": { "city_and_state": "Detroit, MI", "black_pop_pct_chg_1940_1970": 0.08, "black_pop_pct_chg_1910_1940": 0.345, "city": "Detroit", "state": "MI", "state_fips": "26", "GISJOIN": "G26022000", "state_full": "Michigan", "place": "Detroit city" }, "geometry": { "type": "Point", "coordinates": [ -83.04575379960238, 42.331426999565444 ] } },
{ "type": "Feature", "properties": { "city_and_state": "Dover, DE", "black_pop_pct_chg_1940_1970": -0.03, "black_pop_pct_chg_1910_1940": -0.01, "city": "Dover", "state": "DE", "state_fips": "10", "GISJOIN": "G10021200", "state_full": "Delaware", "place": "Dover city" }, "geometry": { "type": "Point", "coordinates": [ -75.524368200392175, 39.158167999879872 ] } },
{ "type": "Feature", "properties": { "city_and_state": "Dubuque, IA", "black_pop_pct_chg_1940_1970": -0.001, "black_pop_pct_chg_1910_1940": 0.0, "city": "Dubuque", "state": "IA", "state_fips": "19", "GISJOIN": "G19022395", "state_full": "Iowa", "place": "Dubuque city" }, "geometry": { "type": "Point", "coordinates": [ -90.664571800612151, 42.500558299766013 ] } },
{ "type": "Feature", "properties": { "city_and_state": "Duluth, MN", "black_pop_pct_chg_1940_1970": -0.002, "black_pop_pct_chg_1910_1940": 0.005, "city": "Duluth", "state": "MN", "state_fips": "27", "GISJOIN": "G27017000", "state_full": "Minnesota", "place": "Duluth city" }, "geometry": { "type": "Point", "coordinates": [ -92.106578699942801, 46.783273099883928 ] } },
{ "type": "Feature", "properties": { "city_and_state": "Durham, NC", "black_pop_pct_chg_1940_1970": 0.011, "black_pop_pct_chg_1910_1940": 0.0, "city": "Durham", "state": "NC", "state_fips": "37", "GISJOIN": "G37019000", "state_full": "North Carolina", "place": "Durham city" }, "geometry": { "type": "Point", "coordinates": [ -78.89861899946176, 35.994032900368204 ] } },
{ "type": "Feature", "properties": { "city_and_state": "El Paso, TX", "black_pop_pct_chg_1940_1970": -0.014, "black_pop_pct_chg_1910_1940": 0.0, "city": "El Paso", "state": "TX", "state_fips": "48", "GISJOIN": "G48024000", "state_full": "Texas", "place": "El Paso city" }, "geometry": { "type": "Point", "coordinates": [ -106.486931400173631, 31.758719800239952 ] } },
{ "type": "Feature", "properties": { "city_and_state": "Elizabeth, NJ", "black_pop_pct_chg_1940_1970": 0.026, "black_pop_pct_chg_1910_1940": 0.11, "city": "Elizabeth", "state": "NJ", "state_fips": "34", "GISJOIN": "G34021000", "state_full": "New Jersey", "place": "Elizabeth city" }, "geometry": { "type": "Point", "coordinates": [ -74.210700599893514, 40.663991600048128 ] } },
{ "type": "Feature", "properties": { "city_and_state": "Erie, PA", "black_pop_pct_chg_1940_1970": 0.007, "black_pop_pct_chg_1910_1940": 0.055, "city": "Erie", "state": "PA", "state_fips": "42", "GISJOIN": "G42024000", "state_full": "Pennsylvania", "place": "Erie city" }, "geometry": { "type": "Point", "coordinates": [ -80.085059000480129, 42.129224100403185 ] } },
{ "type": "Feature", "properties": { "city_and_state": "Eugene, OR", "black_pop_pct_chg_1940_1970": 0.0, "black_pop_pct_chg_1910_1940": 0.008, "city": "Eugene", "state": "OR", "state_fips": "41", "GISJOIN": "G41023850", "state_full": "Oregon", "place": "Eugene city" }, "geometry": { "type": "Point", "coordinates": [ -123.086753600057378, 44.052069100366836 ] } },
{ "type": "Feature", "properties": { "city_and_state": "Evansville, IN", "black_pop_pct_chg_1940_1970": -0.019, "black_pop_pct_chg_1910_1940": 0.002, "city": "Evansville", "state": "IN", "state_fips": "18", "GISJOIN": "G18022000", "state_full": "Indiana", "place": "Evansville city" }, "geometry": { "type": "Point", "coordinates": [ -87.555848199531454, 37.974764400158136 ] } },
{ "type": "Feature", "properties": { "city_and_state": null, "black_pop_pct_chg_1940_1970": null, "black_pop_pct_chg_1910_1940": null, "city": null, "state": null, "state_fips": null, "GISJOIN": null, "state_full": null, "place": null }, "geometry": null },
{ "type": "Feature", "properties": { "city_and_state": "Fall River, MA", "black_pop_pct_chg_1940_1970": 0.001, "black_pop_pct_chg_1910_1940": 0.001, "city": "Fall River", "state": "MA", "state_fips": "25", "GISJOIN": "G25023000", "state_full": "Massachusetts", "place": "Fall River city" }, "geometry": { "type": "Point", "coordinates": [ -71.155045100521335, 41.701491199791711 ] } },
{ "type": "Feature", "properties": { "city_and_state": "Fargo, ND", "black_pop_pct_chg_1940_1970": -0.006, "black_pop_pct_chg_1910_1940": 0.0, "city": "Fargo", "state": "ND", "state_fips": "38", "GISJOIN": "G38025700", "state_full": "North Dakota", "place": "Fargo city" }, "geometry": { "type": "Point", "coordinates": [ -96.789803400143754, 46.877186300251779 ] } },
{ "type": "Feature", "properties": { "city_and_state": "Fayetteville, NC", "black_pop_pct_chg_1940_1970": -0.069, "black_pop_pct_chg_1910_1940": -0.016, "city": "Fayetteville", "state": "NC", "state_fips": "37", "GISJOIN": "G37022920", "state_full": "North Carolina", "place": "Fayetteville city" }, "geometry": { "type": "Point", "coordinates": [ -78.878358499671648, 35.052664099979189 ] } },
{ "type": "Feature", "properties": { "city_and_state": "Flint, MI", "black_pop_pct_chg_1940_1970": 0.033, "black_pop_pct_chg_1910_1940": 0.237, "city": "Flint", "state": "MI", "state_fips": "26", "GISJOIN": "G26029000", "state_full": "Michigan", "place": "Flint city" }, "geometry": { "type": "Point", "coordinates": [ -83.687456200404696, 43.012527399943068 ] } },
{ "type": "Feature", "properties": { "city_and_state": "Fort Smith, AR", "black_pop_pct_chg_1940_1970": -0.071, "black_pop_pct_chg_1910_1940": -0.046, "city": "Fort Smith", "state": "AR", "state_fips": "05", "GISJOIN": "G05024550", "state_full": "Arkansas", "place": "Fort Smith city" }, "geometry": { "type": "Point", "coordinates": [ -94.398547499994052, 35.385924200177641 ] } },
{ "type": "Feature", "properties": { "city_and_state": "Fort Wayne, IN", "black_pop_pct_chg_1940_1970": 0.012, "black_pop_pct_chg_1910_1940": 0.085, "city": "Fort Wayne", "state": "IN", "state_fips": "18", "GISJOIN": "G18025000", "state_full": "Indiana", "place": "Fort Wayne city" }, "geometry": { "type": "Point", "coordinates": [ -85.128859700302002, 41.130604100295315 ] } },
{ "type": "Feature", "properties": { "city_and_state": "Fort Worth, TX", "black_pop_pct_chg_1940_1970": -0.039, "black_pop_pct_chg_1910_1940": 0.057, "city": "Fort Worth", "state": "TX", "state_fips": "48", "GISJOIN": "G48027000", "state_full": "Texas", "place": "Fort Worth city" }, "geometry": { "type": "Point", "coordinates": [ -97.320849599749991, 32.725409000374746 ] } },
{ "type": "Feature", "properties": { "city_and_state": "Frederick, MD", "black_pop_pct_chg_1940_1970": -0.026, "black_pop_pct_chg_1910_1940": 0.009, "city": "Frederick", "state": "MD", "state_fips": "24", "GISJOIN": "G24030325", "state_full": "Maryland", "place": "Frederick city" }, "geometry": { "type": "Point", "coordinates": [ -77.410540900099107, 39.414268800195224 ] } },
{ "type": "Feature", "properties": { "city_and_state": "Fresno, CA", "black_pop_pct_chg_1940_1970": 0.023, "black_pop_pct_chg_1910_1940": 0.063, "city": "Fresno", "state": "CA", "state_fips": "06", "GISJOIN": "G06027000", "state_full": "California", "place": "Fresno city" }, "geometry": { "type": "Point", "coordinates": [ -119.772366100022992, 36.74772720038402 ] } },
{ "type": "Feature", "properties": { "city_and_state": "Galveston, TX", "black_pop_pct_chg_1940_1970": 0.036, "black_pop_pct_chg_1910_1940": 0.04, "city": "Galveston", "state": "TX", "state_fips": "48", "GISJOIN": "G48028068", "state_full": "Texas", "place": "Galveston city" }, "geometry": { "type": "Point", "coordinates": [ -94.797777799541691, 29.301388900444746 ] } },
{ "type": "Feature", "properties": { "city_and_state": "Gary, IN", "black_pop_pct_chg_1940_1970": 0.16, "black_pop_pct_chg_1910_1940": 0.346, "city": "Gary", "state": "IN", "state_fips": "18", "GISJOIN": "G18027000", "state_full": "Indiana", "place": "Gary city" }, "geometry": { "type": "Point", "coordinates": [ -87.346427099535063, 41.593369599585273 ] } },
{ "type": "Feature", "properties": { "city_and_state": "Glendale, AZ", "black_pop_pct_chg_1940_1970": null, "black_pop_pct_chg_1910_1940": -0.003, "city": "Glendale", "state": "AZ", "state_fips": "04", "GISJOIN": "G04027820", "state_full": "Arizona", "place": "Glendale city" }, "geometry": { "type": "Point", "coordinates": [ -112.185986600132395, 33.538652300383198 ] } },
{ "type": "Feature", "properties": { "city_and_state": "Glendale, CA", "black_pop_pct_chg_1940_1970": null, "black_pop_pct_chg_1910_1940": 0.0, "city": "Glendale", "state": "CA", "state_fips": "06", "GISJOIN": "G06030000", "state_full": "California", "place": "Glendale city" }, "geometry": { "type": "Point", "coordinates": [ -118.255074999900472, 34.14250779958445 ] } },
{ "type": "Feature", "properties": { "city_and_state": "Grand Forks, ND", "black_pop_pct_chg_1940_1970": -0.004, "black_pop_pct_chg_1910_1940": 0.002, "city": "Grand Forks", "state": "ND", "state_fips": "38", "GISJOIN": "G38032060", "state_full": "North Dakota", "place": "Grand Forks city" }, "geometry": { "type": "Point", "coordinates": [ -97.032854699923547, 47.925256800311224 ] } },
{ "type": "Feature", "properties": { "city_and_state": "Grand Island, NE", "black_pop_pct_chg_1940_1970": -0.007, "black_pop_pct_chg_1910_1940": -0.002, "city": "Grand Island", "state": "NE", "state_fips": "31", "GISJOIN": "G31019595", "state_full": "Nebraska", "place": "Grand Island city" }, "geometry": { "type": "Point", "coordinates": [ -98.342006799748248, 40.925012299660956 ] } },
{ "type": "Feature", "properties": { "city_and_state": "Grand Rapids, MI", "black_pop_pct_chg_1940_1970": 0.01, "black_pop_pct_chg_1910_1940": 0.097, "city": "Grand Rapids", "state": "MI", "state_fips": "26", "GISJOIN": "G26034000", "state_full": "Michigan", "place": "Grand Rapids city" }, "geometry": { "type": "Point", "coordinates": [ -85.668086299559093, 42.963359899556806 ] } },
{ "type": "Feature", "properties": { "city_and_state": "Great Falls, MT", "black_pop_pct_chg_1940_1970": -0.003, "black_pop_pct_chg_1910_1940": 0.0, "city": "Great Falls", "state": "MT", "state_fips": "30", "GISJOIN": "G30032800", "state_full": "Montana", "place": "Great Falls city" }, "geometry": { "type": "Point", "coordinates": [ -111.300808300372523, 47.500235399770844 ] } },
{ "type": "Feature", "properties": { "city_and_state": "Greensboro, NC", "black_pop_pct_chg_1940_1970": -0.084, "black_pop_pct_chg_1910_1940": 0.007, "city": "Greensboro", "state": "NC", "state_fips": "37", "GISJOIN": "G37028000", "state_full": "North Carolina", "place": "Greensboro city" }, "geometry": { "type": "Point", "coordinates": [ -79.791975400326862, 36.072635500004644 ] } },
{ "type": "Feature", "properties": { "city_and_state": "Greenville, SC", "black_pop_pct_chg_1940_1970": 0.001, "black_pop_pct_chg_1910_1940": -0.09, "city": "Greenville", "state": "SC", "state_fips": "45", "GISJOIN": "G45030850", "state_full": "South Carolina", "place": "Greenville city" }, "geometry": { "type": "Point", "coordinates": [ -82.394010500507775, 34.85261760009098 ] } },
{ "type": "Feature", "properties": { "city_and_state": "Hagerstown, MD", "black_pop_pct_chg_1940_1970": -0.029, "black_pop_pct_chg_1910_1940": 0.008, "city": "Hagerstown", "state": "MD", "state_fips": "24", "GISJOIN": "G24036075", "state_full": "Maryland", "place": "Hagerstown city" }, "geometry": { "type": "Point", "coordinates": [ -77.719993200319365, 39.641762899725009 ] } },
{ "type": "Feature", "properties": { "city_and_state": "Hammond, IN", "black_pop_pct_chg_1940_1970": 0.007, "black_pop_pct_chg_1910_1940": 0.034, "city": "Hammond", "state": "IN", "state_fips": "18", "GISJOIN": "G18031000", "state_full": "Indiana", "place": "Hammond city" }, "geometry": { "type": "Point", "coordinates": [ -87.500041199798417, 41.58336879982356 ] } },
{ "type": "Feature", "properties": { "city_and_state": "Hampton, VA", "black_pop_pct_chg_1940_1970": -0.099, "black_pop_pct_chg_1910_1940": -0.044, "city": "Hampton", "state": "VA", "state_fips": "51", "GISJOIN": "G51035000", "state_full": "Virginia", "place": "Hampton city" }, "geometry": { "type": "Point", "coordinates": [ -76.345221800475954, 37.029868699798655 ] } },
{ "type": "Feature", "properties": { "city_and_state": "Hartford, CT", "black_pop_pct_chg_1940_1970": 0.025, "black_pop_pct_chg_1910_1940": 0.236, "city": "Hartford", "state": "CT", "state_fips": "09", "GISJOIN": "G09037000", "state_full": "Connecticut", "place": "Hartford city" }, "geometry": { "type": "Point", "coordinates": [ -72.685093199634451, 41.76371110029288 ] } },
{ "type": "Feature", "properties": { "city_and_state": "Helena, MT", "black_pop_pct_chg_1940_1970": -0.024, "black_pop_pct_chg_1910_1940": -0.008, "city": "Helena", "state": "MT", "state_fips": "30", "GISJOIN": "G30035600", "state_full": "Montana", "place": "Helena city" }, "geometry": { "type": "Point", "coordinates": [ -112.036109000593299, 46.592712200288872 ] } },
{ "type": "Feature", "properties": { "city_and_state": "Hilo, HI", "black_pop_pct_chg_1940_1970": null, "black_pop_pct_chg_1910_1940": null, "city": "Hilo", "state": "HI", "state_fips": "15", "GISJOIN": null, "state_full": null, "place": null }, "geometry": null },
{ "type": "Feature", "properties": { "city_and_state": "Honolulu, HI", "black_pop_pct_chg_1940_1970": null, "black_pop_pct_chg_1910_1940": null, "city": "Honolulu", "state": "HI", "state_fips": "15", "GISJOIN": null, "state_full": null, "place": null }, "geometry": null },
{ "type": "Feature", "properties": { "city_and_state": "Houston, TX", "black_pop_pct_chg_1940_1970": -0.079, "black_pop_pct_chg_1910_1940": 0.032, "city": "Houston", "state": "TX", "state_fips": "48", "GISJOIN": "G48035000", "state_full": "Texas", "place": "Houston city" }, "geometry": { "type": "Point", "coordinates": [ -95.363271499870464, 29.76328360038158 ] } },
{ "type": "Feature", "properties": { "city_and_state": "Huntington Beach, CA", "black_pop_pct_chg_1940_1970": null, "black_pop_pct_chg_1910_1940": null, "city": "Huntington Beach", "state": "CA", "state_fips": "06", "GISJOIN": "G06036000", "state_full": "California", "place": "Huntington Beach city" }, "geometry": { "type": "Point", "coordinates": [ -117.999226500082841, 33.660296999925286 ] } },
{ "type": "Feature", "properties": { "city_and_state": "Huntington, WV", "black_pop_pct_chg_1940_1970": -0.012, "black_pop_pct_chg_1910_1940": 0.002, "city": "Huntington", "state": "WV", "state_fips": "54", "GISJOIN": "G54039460", "state_full": "West Virginia", "place": "Huntington city" }, "geometry": { "type": "Point", "coordinates": [ -82.44515400036299, 38.419249600034419 ] } },
{ "type": "Feature", "properties": { "city_and_state": "Huntsville, AL", "black_pop_pct_chg_1940_1970": -0.074, "black_pop_pct_chg_1910_1940": -0.24, "city": "Huntsville", "state": "AL", "state_fips": "01", "GISJOIN": "G01037000", "state_full": "Alabama", "place": "Huntsville city" }, "geometry": { "type": "Point", "coordinates": [ -86.586103699444351, 34.730368800265659 ] } },
{ "type": "Feature", "properties": { "city_and_state": "Idaho Falls, ID", "black_pop_pct_chg_1940_1970": -0.001, "black_pop_pct_chg_1910_1940": -0.003, "city": "Idaho Falls", "state": "ID", "state_fips": "16", "GISJOIN": "G16039700", "state_full": "Idaho", "place": "Idaho Falls city" }, "geometry": { "type": "Point", "coordinates": [ -112.034137399752808, 43.466580899646189 ] } },
{ "type": "Feature", "properties": { "city_and_state": "Independence, MO", "black_pop_pct_chg_1940_1970": -0.058, "black_pop_pct_chg_1910_1940": -0.041, "city": "Independence", "state": "MO", "state_fips": "29", "GISJOIN": "G29035000", "state_full": "Missouri", "place": "Independence city" }, "geometry": { "type": "Point", "coordinates": [ -94.415506799963254, 39.091116099959862 ] } },
{ "type": "Feature", "properties": { "city_and_state": "Indianapolis, IN", "black_pop_pct_chg_1940_1970": 0.039, "black_pop_pct_chg_1910_1940": 0.048, "city": "Indianapolis", "state": "IN", "state_fips": "18", "GISJOIN": "G18036003", "state_full": "Indiana", "place": "Indianapolis city (balance)" }, "geometry": { "type": "Point", "coordinates": [ -86.158042299572045, 39.76837649995398 ] } },
{ "type": "Feature", "properties": { "city_and_state": "Jackson, MS", "black_pop_pct_chg_1940_1970": -0.106, "black_pop_pct_chg_1910_1940": 0.006, "city": "Jackson", "state": "MS", "state_fips": "28", "GISJOIN": "G28036000", "state_full": "Mississippi", "place": "Jackson city" }, "geometry": { "type": "Point", "coordinates": [ -90.18481029966587, 32.298757299635511 ] } },
{ "type": "Feature", "properties": { "city_and_state": "Jacksonville, FL", "black_pop_pct_chg_1940_1970": -0.151, "black_pop_pct_chg_1910_1940": -0.134, "city": "Jacksonville", "state": "FL", "state_fips": "12", "GISJOIN": "G12035000", "state_full": "Florida", "place": "Jacksonville city" }, "geometry": { "type": "Point", "coordinates": [ -81.655651000130902, 30.332183799750013 ] } },
{ "type": "Feature", "properties": { "city_and_state": "Jersey City, NJ", "black_pop_pct_chg_1940_1970": 0.022, "black_pop_pct_chg_1910_1940": 0.165, "city": "Jersey City", "state": "NJ", "state_fips": "34", "GISJOIN": "G34036000", "state_full": "New Jersey", "place": "Jersey City city" }, "geometry": { "type": "Point", "coordinates": [ -74.077641699774716, 40.728157500293754 ] } },
{ "type": "Feature", "properties": { "city_and_state": null, "black_pop_pct_chg_1940_1970": null, "black_pop_pct_chg_1910_1940": null, "city": null, "state": null, "state_fips": null, "GISJOIN": null, "state_full": null, "place": null }, "geometry": null },
{ "type": "Feature", "properties": { "city_and_state": "Kansas City, KS", "black_pop_pct_chg_1940_1970": 0.06, "black_pop_pct_chg_1910_1940": 0.031, "city": "Kansas City", "state": "KS", "state_fips": "20", "GISJOIN": "G20036000", "state_full": "Kansas", "place": "Kansas City city" }, "geometry": { "type": "Point", "coordinates": [ -94.627457000308681, 39.114170799891717 ] } },
{ "type": "Feature", "properties": { "city_and_state": "Kansas City, MO", "black_pop_pct_chg_1940_1970": 0.009, "black_pop_pct_chg_1910_1940": 0.117, "city": "Kansas City", "state": "MO", "state_fips": "29", "GISJOIN": "G29038000", "state_full": "Missouri", "place": "Kansas City city" }, "geometry": { "type": "Point", "coordinates": [ -94.578566699481726, 39.099726599713094 ] } },
{ "type": "Feature", "properties": { "city_and_state": "Key West, FL", "black_pop_pct_chg_1940_1970": -0.095, "black_pop_pct_chg_1910_1940": -0.065, "city": "Key West", "state": "FL", "state_fips": "12", "GISJOIN": "G12036550", "state_full": "Florida", "place": "Key West city" }, "geometry": { "type": "Point", "coordinates": [ -81.782591399880801, 24.555702500379365 ] } },
{ "type": "Feature", "properties": { "city_and_state": "Knoxville, TN", "black_pop_pct_chg_1940_1970": -0.066, "black_pop_pct_chg_1910_1940": -0.017, "city": "Knoxville", "state": "TN", "state_fips": "47", "GISJOIN": "G47040000", "state_full": "Tennessee", "place": "Knoxville city" }, "geometry": { "type": "Point", "coordinates": [ -83.920739200348848, 35.960638400265829 ] } },
{ "type": "Feature", "properties": { "city_and_state": "Lansing, MI", "black_pop_pct_chg_1940_1970": 0.009, "black_pop_pct_chg_1910_1940": 0.072, "city": "Lansing", "state": "MI", "state_fips": "26", "GISJOIN": "G26046000", "state_full": "Michigan", "place": "Lansing city" }, "geometry": { "type": "Point", "coordinates": [ -84.555534699993487, 42.732535000409605 ] } },
{ "type": "Feature", "properties": { "city_and_state": "Laramie, WY", "black_pop_pct_chg_1940_1970": 0.0, "black_pop_pct_chg_1910_1940": 0.002, "city": "Laramie", "state": "WY", "state_fips": "56", "GISJOIN": "G56045050", "state_full": "Wyoming", "place": "Laramie city" }, "geometry": { "type": "Point", "coordinates": [ -105.591100700471785, 41.311366899931379 ] } },
{ "type": "Feature", "properties": { "city_and_state": "Laredo, TX", "black_pop_pct_chg_1940_1970": 0.001, "black_pop_pct_chg_1910_1940": 0.002, "city": "Laredo", "state": "TX", "state_fips": "48", "GISJOIN": "G48041464", "state_full": "Texas", "place": "Laredo city" }, "geometry": { "type": "Point", "coordinates": [ -99.507542099791408, 27.506407000129997 ] } },
{ "type": "Feature", "properties": { "city_and_state": "Las Vegas, NV", "black_pop_pct_chg_1940_1970": null, "black_pop_pct_chg_1910_1940": 0.092, "city": "Las Vegas", "state": "NV", "state_fips": "32", "GISJOIN": "G32040000", "state_full": "Nevada", "place": "Las Vegas city" }, "geometry": { "type": "Point", "coordinates": [ -115.137223000017741, 36.174970500209795 ] } },
{ "type": "Feature", "properties": { "city_and_state": "Leavenworth, KS", "black_pop_pct_chg_1940_1970": -0.003, "black_pop_pct_chg_1910_1940": -0.018, "city": "Leavenworth", "state": "KS", "state_fips": "20", "GISJOIN": "G20039000", "state_full": "Kansas", "place": "Leavenworth city" }, "geometry": { "type": "Point", "coordinates": [ -94.922463700104075, 39.311111200129574 ] } },
{ "type": "Feature", "properties": { "city_and_state": "Lewiston, ME", "black_pop_pct_chg_1940_1970": -0.002, "black_pop_pct_chg_1910_1940": 0.001, "city": "Lewiston", "state": "ME", "state_fips": "23", "GISJOIN": "G23038740", "state_full": "Maine", "place": "Lewiston city" }, "geometry": { "type": "Point", "coordinates": [ -70.214776400663609, 44.10035099994181 ] } },
{ "type": "Feature", "properties": { "city_and_state": "Lexington, KY", "black_pop_pct_chg_1940_1970": -0.052, "black_pop_pct_chg_1910_1940": -0.092, "city": "Lexington", "state": "KY", "state_fips": "21", "GISJOIN": null, "state_full": null, "place": null }, "geometry": null },
{ "type": "Feature", "properties": { "city_and_state": "Lincoln, NE", "black_pop_pct_chg_1940_1970": -0.007, "black_pop_pct_chg_1910_1940": 0.005, "city": "Lincoln", "state": "NE", "state_fips": "31", "GISJOIN": "G31028000", "state_full": "Nebraska", "place": "Lincoln city" }, "geometry": { "type": "Point", "coordinates": [ -96.666959900238098, 40.800001099801875 ] } },
{ "type": "Feature", "properties": { "city_and_state": "Little Rock, AR", "black_pop_pct_chg_1940_1970": -0.066, "black_pop_pct_chg_1910_1940": -0.001, "city": "Little Rock", "state": "AR", "state_fips": "05", "GISJOIN": "G05041000", "state_full": "Arkansas", "place": "Little Rock city" }, "geometry": { "type": "Point", "coordinates": [ -92.28959480001096, 34.746480899556282 ] } },
{ "type": "Feature", "properties": { "city_and_state": "Long Beach, CA", "black_pop_pct_chg_1940_1970": -0.002, "black_pop_pct_chg_1910_1940": 0.049, "city": "Long Beach", "state": "CA", "state_fips": "06", "GISJOIN": "G06043000", "state_full": "California", "place": "Long Beach city" }, "geometry": { "type": "Point", "coordinates": [ -118.189234800261829, 33.766962299497948 ] } },
{ "type": "Feature", "properties": { "city_and_state": "Los Angeles, CA", "black_pop_pct_chg_1940_1970": 0.019, "black_pop_pct_chg_1910_1940": 0.136, "city": "Los Angeles", "state": "CA", "state_fips": "06", "GISJOIN": "G06044000", "state_full": "California", "place": "Los Angeles city" }, "geometry": { "type": "Point", "coordinates": [ -118.24368489980526, 34.052234200375707 ] } },
{ "type": "Feature", "properties": { "city_and_state": "Louisville, KY", "black_pop_pct_chg_1940_1970": -0.033, "black_pop_pct_chg_1910_1940": 0.09, "city": "Louisville", "state": "KY", "state_fips": "21", "GISJOIN": null, "state_full": null, "place": null }, "geometry": null },
{ "type": "Feature", "properties": { "city_and_state": "Lowell, MA", "black_pop_pct_chg_1940_1970": 0.0, "black_pop_pct_chg_1910_1940": 0.007, "city": "Lowell", "state": "MA", "state_fips": "25", "GISJOIN": "G25037000", "state_full": "Massachusetts", "place": "Lowell city" }, "geometry": { "type": "Point", "coordinates": [ -71.316171799771865, 42.633424699918734 ] } },
{ "type": "Feature", "properties": { "city_and_state": "Lynn, MA", "black_pop_pct_chg_1940_1970": 0.0, "black_pop_pct_chg_1910_1940": 0.019, "city": "Lynn", "state": "MA", "state_fips": "25", "GISJOIN": "G25037490", "state_full": "Massachusetts", "place": "Lynn city" }, "geometry": { "type": "Point", "coordinates": [ -70.949493900224724, 42.466763000406715 ] } },
{ "type": "Feature", "properties": { "city_and_state": "Macon, GA", "black_pop_pct_chg_1940_1970": -0.004, "black_pop_pct_chg_1910_1940": -0.069, "city": "Macon", "state": "GA", "state_fips": "13", "GISJOIN": "G13049000", "state_full": "Georgia", "place": "Macon city" }, "geometry": { "type": "Point", "coordinates": [ -83.632402199615115, 32.840694599516233 ] } },
{ "type": "Feature", "properties": { "city_and_state": "Madison, WI", "black_pop_pct_chg_1940_1970": 0.0, "black_pop_pct_chg_1910_1940": 0.01, "city": "Madison", "state": "WI", "state_fips": "55", "GISJOIN": "G55048000", "state_full": "Wisconsin", "place": "Madison city" }, "geometry": { "type": "Point", "coordinates": [ -89.401230199626099, 43.073051699758395 ] } },
{ "type": "Feature", "properties": { "city_and_state": "Manchester, NH", "black_pop_pct_chg_1940_1970": 0.0, "black_pop_pct_chg_1910_1940": 0.002, "city": "Manchester", "state": "NH", "state_fips": "33", "GISJOIN": "G33045140", "state_full": "New Hampshire", "place": "Manchester city" }, "geometry": { "type": "Point", "coordinates": [ -71.454789100409371, 42.995639699723455 ] } },
{ "type": "Feature", "properties": { "city_and_state": "Memphis, TN", "black_pop_pct_chg_1940_1970": 0.015, "black_pop_pct_chg_1910_1940": -0.026, "city": "Memphis", "state": "TN", "state_fips": "47", "GISJOIN": "G47048000", "state_full": "Tennessee", "place": "Memphis city" }, "geometry": { "type": "Point", "coordinates": [ -90.048980099910409, 35.149534300019603 ] } },
{ "type": "Feature", "properties": { "city_and_state": "Meridian, MS", "black_pop_pct_chg_1940_1970": -0.038, "black_pop_pct_chg_1910_1940": -0.027, "city": "Meridian", "state": "MS", "state_fips": "28", "GISJOIN": "G28046640", "state_full": "Mississippi", "place": "Meridian city" }, "geometry": { "type": "Point", "coordinates": [ -88.703655999893826, 32.364309799607554 ] } },
{ "type": "Feature", "properties": { "city_and_state": "Mesa, AZ", "black_pop_pct_chg_1940_1970": null, "black_pop_pct_chg_1910_1940": -0.033, "city": "Mesa", "state": "AZ", "state_fips": "04", "GISJOIN": "G04046000", "state_full": "Arizona", "place": "Mesa city" }, "geometry": { "type": "Point", "coordinates": [ -111.82264020024914, 33.422268500116836 ] } },
{ "type": "Feature", "properties": { "city_and_state": "Miami, FL", "black_pop_pct_chg_1940_1970": -0.199, "black_pop_pct_chg_1910_1940": 0.013, "city": "Miami", "state": "FL", "state_fips": "12", "GISJOIN": "G12045000", "state_full": "Florida", "place": "Miami city" }, "geometry": { "type": "Point", "coordinates": [ -80.193658900299738, 25.774265800207697 ] } },
{ "type": "Feature", "properties": { "city_and_state": "Milwaukee, WI", "black_pop_pct_chg_1940_1970": 0.012, "black_pop_pct_chg_1910_1940": 0.132, "city": "Milwaukee", "state": "WI", "state_fips": "55", "GISJOIN": "G55053000", "state_full": "Wisconsin", "place": "Milwaukee city" }, "geometry": { "type": "Point", "coordinates": [ -87.90647360033249, 43.038902500306733 ] } },
{ "type": "Feature", "properties": { "city_and_state": "Minneapolis, MN", "black_pop_pct_chg_1940_1970": 0.001, "black_pop_pct_chg_1910_1940": 0.034, "city": "Minneapolis", "state": "MN", "state_fips": "27", "GISJOIN": "G27043000", "state_full": "Minnesota", "place": "Minneapolis city" }, "geometry": { "type": "Point", "coordinates": [ -93.263836099699617, 44.979965400245021 ] } },
{ "type": "Feature", "properties": { "city_and_state": "Minot, ND", "black_pop_pct_chg_1940_1970": -0.007, "black_pop_pct_chg_1910_1940": 0.002, "city": "Minot", "state": "ND", "state_fips": "38", "GISJOIN": "G38053380", "state_full": "North Dakota", "place": "Minot city" }, "geometry": { "type": "Point", "coordinates": [ -101.296273199492845, 48.232509499656778 ] } },
{ "type": "Feature", "properties": { "city_and_state": "Mobile, AL", "black_pop_pct_chg_1940_1970": -0.073, "black_pop_pct_chg_1910_1940": -0.015, "city": "Mobile", "state": "AL", "state_fips": "01", "GISJOIN": "G01050000", "state_full": "Alabama", "place": "Mobile city" }, "geometry": { "type": "Point", "coordinates": [ -88.043054100108378, 30.694356599783085 ] } },
{ "type": "Feature", "properties": { "city_and_state": "Montgomery, AL", "black_pop_pct_chg_1940_1970": -0.064, "black_pop_pct_chg_1910_1940": -0.108, "city": "Montgomery", "state": "AL", "state_fips": "01", "GISJOIN": "G01051000", "state_full": "Alabama", "place": "Montgomery city" }, "geometry": { "type": "Point", "coordinates": [ -86.299968899648846, 32.366805200144071 ] } },
{ "type": "Feature", "properties": { "city_and_state": "Muscogee, OK", "black_pop_pct_chg_1940_1970": -0.106, "black_pop_pct_chg_1910_1940": -0.018, "city": "Muscogee", "state": "OK", "state_fips": "40", "GISJOIN": null, "state_full": null, "place": null }, "geometry": null },
{ "type": "Feature", "properties": { "city_and_state": "Nashua, NH", "black_pop_pct_chg_1940_1970": 0.001, "black_pop_pct_chg_1910_1940": 0.003, "city": "Nashua", "state": "NH", "state_fips": "33", "GISJOIN": "G33050260", "state_full": "New Hampshire", "place": "Nashua city" }, "geometry": { "type": "Point", "coordinates": [ -71.46756600034908, 42.765366199944907 ] } },
{ "type": "Feature", "properties": { "city_and_state": "Nashville, TN", "black_pop_pct_chg_1940_1970": -0.048, "black_pop_pct_chg_1910_1940": -0.087, "city": "Nashville", "state": "TN", "state_fips": "47", "GISJOIN": null, "state_full": null, "place": null }, "geometry": null },
{ "type": "Feature", "properties": { "city_and_state": "Natchez, MS", "black_pop_pct_chg_1940_1970": -0.045, "black_pop_pct_chg_1910_1940": -0.018, "city": "Natchez", "state": "MS", "state_fips": "28", "GISJOIN": "G28050440", "state_full": "Mississippi", "place": "Natchez city" }, "geometry": { "type": "Point", "coordinates": [ -91.403171000141782, 31.560444199772295 ] } },
{ "type": "Feature", "properties": { "city_and_state": "New Albany, IN", "black_pop_pct_chg_1940_1970": -0.028, "black_pop_pct_chg_1910_1940": 0.0, "city": "New Albany", "state": "IN", "state_fips": "18", "GISJOIN": "G18052326", "state_full": "Indiana", "place": "New Albany city" }, "geometry": { "type": "Point", "coordinates": [ -85.824131199969557, 38.285624699704137 ] } },
{ "type": "Feature", "properties": { "city_and_state": "New Bedford, MA", "black_pop_pct_chg_1940_1970": 0.009, "black_pop_pct_chg_1910_1940": -0.004, "city": "New Bedford", "state": "MA", "state_fips": "25", "GISJOIN": "G25045000", "state_full": "Massachusetts", "place": "New Bedford city" }, "geometry": { "type": "Point", "coordinates": [ -70.934204999813261, 41.636215200252181 ] } },
{ "type": "Feature", "properties": { "city_and_state": "New Bern, NC", "black_pop_pct_chg_1940_1970": -0.073, "black_pop_pct_chg_1910_1940": -0.109, "city": "New Bern", "state": "NC", "state_fips": "37", "GISJOIN": "G37046340", "state_full": "North Carolina", "place": "New Bern city" }, "geometry": { "type": "Point", "coordinates": [ -77.044114299733977, 35.108493099919272 ] } },
{ "type": "Feature", "properties": { "city_and_state": "New Castle, DE", "black_pop_pct_chg_1940_1970": -0.02, "black_pop_pct_chg_1910_1940": -0.032, "city": "New Castle", "state": "DE", "state_fips": "10", "GISJOIN": "G10050800", "state_full": "Delaware", "place": "New Castle city" }, "geometry": { "type": "Point", "coordinates": [ -75.566313199558081, 39.662057200010857 ] } },
{ "type": "Feature", "properties": { "city_and_state": "New Haven, CT", "black_pop_pct_chg_1940_1970": 0.012, "black_pop_pct_chg_1910_1940": 0.224, "city": "New Haven", "state": "CT", "state_fips": "09", "GISJOIN": "G09052000", "state_full": "Connecticut", "place": "New Haven city" }, "geometry": { "type": "Point", "coordinates": [ -72.928157800311382, 41.308152699780379 ] } },
{ "type": "Feature", "properties": { "city_and_state": "New London, CT", "black_pop_pct_chg_1940_1970": 0.01, "black_pop_pct_chg_1910_1940": 0.082, "city": "New London", "state": "CT", "state_fips": "09", "GISJOIN": "G09052280", "state_full": "Connecticut", "place": "New London city" }, "geometry": { "type": "Point", "coordinates": [ -72.09952090018804, 41.35565390033247 ] } },
{ "type": "Feature", "properties": { "city_and_state": "New Orleans, LA", "black_pop_pct_chg_1940_1970": 0.038, "black_pop_pct_chg_1910_1940": 0.149, "city": "New Orleans", "state": "LA", "state_fips": "22", "GISJOIN": "G22055000", "state_full": "Louisiana", "place": "New Orleans city" }, "geometry": { "type": "Point", "coordinates": [ -90.075072000242841, 29.954648199764463 ] } },
{ "type": "Feature", "properties": { "city_and_state": "New York, NY", "black_pop_pct_chg_1940_1970": 0.042, "black_pop_pct_chg_1910_1940": 0.15, "city": "New York", "state": "NY", "state_fips": "36", "GISJOIN": "G36051000", "state_full": "New York", "place": "New York city" }, "geometry": { "type": "Point", "coordinates": [ -74.005972899905188, 40.714269099562479 ] } },
{ "type": "Feature", "properties": { "city_and_state": "Newark, DE", "black_pop_pct_chg_1940_1970": null, "black_pop_pct_chg_1910_1940": -0.084, "city": "Newark", "state": "DE", "state_fips": "10", "GISJOIN": "G10050670", "state_full": "Delaware", "place": "Newark city" }, "geometry": { "type": "Point", "coordinates": [ -75.749657199599227, 39.683722599600443 ] } },
{ "type": "Feature", "properties": { "city_and_state": "Newark, NJ", "black_pop_pct_chg_1940_1970": 0.079, "black_pop_pct_chg_1910_1940": 0.436, "city": "Newark", "state": "NJ", "state_fips": "34", "GISJOIN": "G34051000", "state_full": "New Jersey", "place": "Newark city" }, "geometry": { "type": "Point", "coordinates": [ -74.172366699978809, 40.735656999944766 ] } },
{ "type": "Feature", "properties": { "city_and_state": "Newport News, VA", "black_pop_pct_chg_1940_1970": 0.053, "black_pop_pct_chg_1910_1940": -0.129, "city": "Newport News", "state": "VA", "state_fips": "51", "GISJOIN": "G51056000", "state_full": "Virginia", "place": "Newport News city" }, "geometry": { "type": "Point", "coordinates": [ -76.428002999559951, 36.978758799541453 ] } },
{ "type": "Feature", "properties": { "city_and_state": "Newport, KY", "black_pop_pct_chg_1940_1970": 0.014, "black_pop_pct_chg_1910_1940": -0.003, "city": "Newport", "state": "KY", "state_fips": "21", "GISJOIN": "G21055884", "state_full": "Kentucky", "place": "Newport city" }, "geometry": { "type": "Point", "coordinates": [ -84.495775700249155, 39.091449000043077 ] } },
{ "type": "Feature", "properties": { "city_and_state": "Newport, RI", "black_pop_pct_chg_1940_1970": -0.004, "black_pop_pct_chg_1910_1940": 0.018, "city": "Newport", "state": "RI", "state_fips": "44", "GISJOIN": "G44049960", "state_full": "Rhode Island", "place": "Newport city" }, "geometry": { "type": "Point", "coordinates": [ -71.312828499797035, 41.49010239990838 ] } },
{ "type": "Feature", "properties": { "city_and_state": "Niagara Falls, NY", "black_pop_pct_chg_1940_1970": 0.004, "black_pop_pct_chg_1910_1940": 0.081, "city": "Niagara Falls", "state": "NY", "state_fips": "36", "GISJOIN": "G36051055", "state_full": "New York", "place": "Niagara Falls city" }, "geometry": { "type": "Point", "coordinates": [ -79.056711100546977, 43.094499900139688 ] } },
{ "type": "Feature", "properties": { "city_and_state": "Norfolk, VA", "black_pop_pct_chg_1940_1970": -0.053, "black_pop_pct_chg_1910_1940": -0.035, "city": "Norfolk", "state": "VA", "state_fips": "51", "GISJOIN": "G51057000", "state_full": "Virginia", "place": "Norfolk city" }, "geometry": { "type": "Point", "coordinates": [ -76.28521829965004, 36.846814600111763 ] } },
{ "type": "Feature", "properties": { "city_and_state": "North Little Rock, AR", "black_pop_pct_chg_1940_1970": -0.081, "black_pop_pct_chg_1910_1940": -0.136, "city": "North Little Rock", "state": "AR", "state_fips": "05", "GISJOIN": "G05050450", "state_full": "Arkansas", "place": "North Little Rock city" }, "geometry": { "type": "Point", "coordinates": [ -92.267094099956424, 34.769536000199992 ] } },
{ "type": "Feature", "properties": { "city_and_state": "Oakland, CA", "black_pop_pct_chg_1940_1970": 0.008, "black_pop_pct_chg_1910_1940": 0.317, "city": "Oakland", "state": "CA", "state_fips": "06", "GISJOIN": "G06053000", "state_full": "California", "place": "Oakland city" }, "geometry": { "type": "Point", "coordinates": [ -122.270802600182421, 37.804372200295667 ] } },
{ "type": "Feature", "properties": { "city_and_state": "Ogden, UT", "black_pop_pct_chg_1940_1970": 0.0, "black_pop_pct_chg_1910_1940": 0.019, "city": "Ogden", "state": "UT", "state_fips": "49", "GISJOIN": "G49055980", "state_full": "Utah", "place": "Ogden city" }, "geometry": { "type": "Point", "coordinates": [ -111.973830400516093, 41.222999999967278 ] } },
{ "type": "Feature", "properties": { "city_and_state": "Oklahoma City, OK", "black_pop_pct_chg_1940_1970": -0.007, "black_pop_pct_chg_1910_1940": 0.042, "city": "Oklahoma City", "state": "OK", "state_fips": "40", "GISJOIN": "G40055000", "state_full": "Oklahoma", "place": "Oklahoma City city" }, "geometry": { "type": "Point", "coordinates": [ -97.516427599478789, 35.4675602000056 ] } },
{ "type": "Feature", "properties": { "city_and_state": "Omaha, NE", "black_pop_pct_chg_1940_1970": 0.018, "black_pop_pct_chg_1910_1940": 0.045, "city": "Omaha", "state": "NE", "state_fips": "31", "GISJOIN": "G31037000", "state_full": "Nebraska", "place": "Omaha city" }, "geometry": { "type": "Point", "coordinates": [ -95.937792000023791, 41.258609600230159 ] } },
{ "type": "Feature", "properties": { "city_and_state": "Orlando, FL", "black_pop_pct_chg_1940_1970": -0.079, "black_pop_pct_chg_1910_1940": 0.01, "city": "Orlando", "state": "FL", "state_fips": "12", "GISJOIN": "G12053000", "state_full": "Florida", "place": "Orlando city" }, "geometry": { "type": "Point", "coordinates": [ -81.379236500179971, 28.538335499688369 ] } },
{ "type": "Feature", "properties": { "city_and_state": "Paterson, NJ", "black_pop_pct_chg_1940_1970": 0.018, "black_pop_pct_chg_1910_1940": 0.238, "city": "Paterson", "state": "NJ", "state_fips": "34", "GISJOIN": "G34057000", "state_full": "New Jersey", "place": "Paterson city" }, "geometry": { "type": "Point", "coordinates": [ -74.171811000494387, 40.916765400305373 ] } },
{ "type": "Feature", "properties": { "city_and_state": "Pawtucket, RI", "black_pop_pct_chg_1940_1970": -0.001, "black_pop_pct_chg_1910_1940": 0.001, "city": "Pawtucket", "state": "RI", "state_fips": "44", "GISJOIN": "G44054640", "state_full": "Rhode Island", "place": "Pawtucket city" }, "geometry": { "type": "Point", "coordinates": [ -71.382555800143024, 41.878710999682575 ] } },
{ "type": "Feature", "properties": { "city_and_state": "Pensacola, FL", "black_pop_pct_chg_1940_1970": -0.115, "black_pop_pct_chg_1910_1940": 0.002, "city": "Pensacola", "state": "FL", "state_fips": "12", "GISJOIN": "G12055925", "state_full": "Florida", "place": "Pensacola city" }, "geometry": { "type": "Point", "coordinates": [ -87.21691490034209, 30.42130899984587 ] } },
{ "type": "Feature", "properties": { "city_and_state": "Peoria, IL", "black_pop_pct_chg_1940_1970": 0.003, "black_pop_pct_chg_1910_1940": 0.088, "city": "Peoria", "state": "IL", "state_fips": "17", "GISJOIN": "G17059000", "state_full": "Illinois", "place": "Peoria city" }, "geometry": { "type": "Point", "coordinates": [ -89.588986400003535, 40.693648800152765 ] } },
{ "type": "Feature", "properties": { "city_and_state": "Petersburg, VA", "black_pop_pct_chg_1940_1970": -0.016, "black_pop_pct_chg_1910_1940": 0.111, "city": "Petersburg", "state": "VA", "state_fips": "51", "GISJOIN": "G51061832", "state_full": "Virginia", "place": "Petersburg city" }, "geometry": { "type": "Point", "coordinates": [ -77.401926700442189, 37.227927900399983 ] } },
{ "type": "Feature", "properties": { "city_and_state": "Philadelphia, PA", "black_pop_pct_chg_1940_1970": 0.075, "black_pop_pct_chg_1910_1940": 0.206, "city": "Philadelphia", "state": "PA", "state_fips": "42", "GISJOIN": "G42060000", "state_full": "Pennsylvania", "place": "Philadelphia city" }, "geometry": { "type": "Point", "coordinates": [ -75.163788999616116, 39.952335000016589 ] } },
{ "type": "Feature", "properties": { "city_and_state": "Phoenix, AZ", "black_pop_pct_chg_1940_1970": 0.036, "black_pop_pct_chg_1910_1940": -0.017, "city": "Phoenix", "state": "AZ", "state_fips": "04", "GISJOIN": "G04055000", "state_full": "Arizona", "place": "Phoenix city" }, "geometry": { "type": "Point", "coordinates": [ -112.074037299798889, 33.448377100294877 ] } },
{ "type": "Feature", "properties": { "city_and_state": "Pine Bluff, AR", "black_pop_pct_chg_1940_1970": -0.077, "black_pop_pct_chg_1910_1940": 0.08, "city": "Pine Bluff", "state": "AR", "state_fips": "05", "GISJOIN": "G05055310", "state_full": "Arkansas", "place": "Pine Bluff city" }, "geometry": { "type": "Point", "coordinates": [ -92.003195500503651, 34.228431200419443 ] } },
{ "type": "Feature", "properties": { "city_and_state": "Pittsburgh, PA", "black_pop_pct_chg_1940_1970": 0.045, "black_pop_pct_chg_1910_1940": 0.109, "city": "Pittsburgh", "state": "PA", "state_fips": "42", "GISJOIN": "G42061000", "state_full": "Pennsylvania", "place": "Pittsburgh city" }, "geometry": { "type": "Point", "coordinates": [ -79.995886399510653, 40.440624799575652 ] } },
{ "type": "Feature", "properties": { "city_and_state": "Pocatello, ID", "black_pop_pct_chg_1940_1970": -0.002, "black_pop_pct_chg_1910_1940": 0.0, "city": "Pocatello", "state": "ID", "state_fips": "16", "GISJOIN": "G16064090", "state_full": "Idaho", "place": "Pocatello city" }, "geometry": { "type": "Point", "coordinates": [ -112.445534400341998, 42.871303199797779 ] } },
{ "type": "Feature", "properties": { "city_and_state": "Portland, ME", "black_pop_pct_chg_1940_1970": 0.0, "black_pop_pct_chg_1910_1940": 0.002, "city": "Portland", "state": "ME", "state_fips": "23", "GISJOIN": "G23060545", "state_full": "Maine", "place": "Portland city" }, "geometry": { "type": "Point", "coordinates": [ -70.255325900135134, 43.661470999623376 ] } },
{ "type": "Feature", "properties": { "city_and_state": "Portland, OR", "black_pop_pct_chg_1940_1970": 0.001, "black_pop_pct_chg_1910_1940": 0.05, "city": "Portland", "state": "OR", "state_fips": "41", "GISJOIN": "G41059000", "state_full": "Oregon", "place": "Portland city" }, "geometry": { "type": "Point", "coordinates": [ -122.676207100755178, 45.523451500273367 ] } },
{ "type": "Feature", "properties": { "city_and_state": "Portsmouth, NH", "black_pop_pct_chg_1940_1970": -0.003, "black_pop_pct_chg_1910_1940": 0.036, "city": "Portsmouth", "state": "NH", "state_fips": "33", "GISJOIN": "G33062900", "state_full": "New Hampshire", "place": "Portsmouth city" }, "geometry": { "type": "Point", "coordinates": [ -70.762553199321118, 43.071755200219009 ] } },
{ "type": "Feature", "properties": { "city_and_state": "Portsmouth, VA", "black_pop_pct_chg_1940_1970": 0.031, "black_pop_pct_chg_1910_1940": 0.018, "city": "Portsmouth", "state": "VA", "state_fips": "51", "GISJOIN": "G51064000", "state_full": "Virginia", "place": "Portsmouth city" }, "geometry": { "type": "Point", "coordinates": [ -76.298274199932777, 36.835425799628297 ] } },
{ "type": "Feature", "properties": { "city_and_state": "Providence, RI", "black_pop_pct_chg_1940_1970": 0.002, "black_pop_pct_chg_1910_1940": 0.063, "city": "Providence", "state": "RI", "state_fips": "44", "GISJOIN": "G44059000", "state_full": "Rhode Island", "place": "Providence city" }, "geometry": { "type": "Point", "coordinates": [ -71.412834299976126, 41.823989099859659 ] } },
{ "type": "Feature", "properties": { "city_and_state": "Provo, UT", "black_pop_pct_chg_1940_1970": 0.001, "black_pop_pct_chg_1910_1940": 0.0, "city": "Provo", "state": "UT", "state_fips": "49", "GISJOIN": "G49062470", "state_full": "Utah", "place": "Provo city" }, "geometry": { "type": "Point", "coordinates": [ -111.658533699944272, 40.233843799963857 ] } },
{ "type": "Feature", "properties": { "city_and_state": "Pueblo, CO", "black_pop_pct_chg_1940_1970": -0.007, "black_pop_pct_chg_1910_1940": -0.005, "city": "Pueblo", "state": "CO", "state_fips": "08", "GISJOIN": "G08062000", "state_full": "Colorado", "place": "Pueblo city" }, "geometry": { "type": "Point", "coordinates": [ -104.609141000136844, 38.254447199628281 ] } },
{ "type": "Feature", "properties": { "city_and_state": "Quincy, IL", "black_pop_pct_chg_1940_1970": -0.015, "black_pop_pct_chg_1910_1940": 0.004, "city": "Quincy", "state": "IL", "state_fips": "17", "GISJOIN": "G17062367", "state_full": "Illinois", "place": "Quincy city" }, "geometry": { "type": "Point", "coordinates": [ -91.409872699498763, 39.935601599739748 ] } },
{ "type": "Feature", "properties": { "city_and_state": "Racine, WI", "black_pop_pct_chg_1940_1970": 0.003, "black_pop_pct_chg_1910_1940": 0.099, "city": "Racine", "state": "WI", "state_fips": "55", "GISJOIN": "G55066000", "state_full": "Wisconsin", "place": "Racine city" }, "geometry": { "type": "Point", "coordinates": [ -87.782852299392246, 42.726130900345062 ] } },
{ "type": "Feature", "properties": { "city_and_state": "Raleigh, NC", "black_pop_pct_chg_1940_1970": -0.046, "black_pop_pct_chg_1910_1940": -0.11, "city": "Raleigh", "state": "NC", "state_fips": "37", "GISJOIN": "G37055000", "state_full": "North Carolina", "place": "Raleigh city" }, "geometry": { "type": "Point", "coordinates": [ -78.638614499547558, 35.772096000228657 ] } },
{ "type": "Feature", "properties": { "city_and_state": "Rapid City, SD", "black_pop_pct_chg_1940_1970": -0.006, "black_pop_pct_chg_1910_1940": 0.003, "city": "Rapid City", "state": "SD", "state_fips": "46", "GISJOIN": "G46052980", "state_full": "South Dakota", "place": "Rapid City city" }, "geometry": { "type": "Point", "coordinates": [ -103.231014899866011, 44.080543399739732 ] } },
{ "type": "Feature", "properties": { "city_and_state": "Reading, PA", "black_pop_pct_chg_1940_1970": 0.009, "black_pop_pct_chg_1910_1940": 0.048, "city": "Reading", "state": "PA", "state_fips": "42", "GISJOIN": "G42063624", "state_full": "Pennsylvania", "place": "Reading city" }, "geometry": { "type": "Point", "coordinates": [ -75.926874700136835, 40.335648299696821 ] } },
{ "type": "Feature", "properties": { "city_and_state": "Reno, NV", "black_pop_pct_chg_1940_1970": 0.002, "black_pop_pct_chg_1910_1940": 0.012, "city": "Reno", "state": "NV", "state_fips": "32", "GISJOIN": "G32060600", "state_full": "Nevada", "place": "Reno city" }, "geometry": { "type": "Point", "coordinates": [ -119.813802699580506, 39.529632899767435 ] } },
{ "type": "Feature", "properties": { "city_and_state": "Richmond, VA", "black_pop_pct_chg_1940_1970": -0.049, "black_pop_pct_chg_1910_1940": 0.102, "city": "Richmond", "state": "VA", "state_fips": "51", "GISJOIN": "G51067000", "state_full": "Virginia", "place": "Richmond city" }, "geometry": { "type": "Point", "coordinates": [ -77.460261699925269, 37.553757500114159 ] } },
{ "type": "Feature", "properties": { "city_and_state": "Riverside, CA", "black_pop_pct_chg_1940_1970": -0.002, "black_pop_pct_chg_1910_1940": 0.026, "city": "Riverside", "state": "CA", "state_fips": "06", "GISJOIN": "G06062000", "state_full": "California", "place": "Riverside city" }, "geometry": { "type": "Point", "coordinates": [ -117.396156399997864, 33.95334869978204 ] } },
{ "type": "Feature", "properties": { "city_and_state": "Roanoke, VA", "black_pop_pct_chg_1940_1970": -0.042, "black_pop_pct_chg_1910_1940": 0.008, "city": "Roanoke", "state": "VA", "state_fips": "51", "GISJOIN": "G51068000", "state_full": "Virginia", "place": "Roanoke city" }, "geometry": { "type": "Point", "coordinates": [ -79.941426700015612, 37.270970400109505 ] } },
{ "type": "Feature", "properties": { "city_and_state": "Rochester, NY", "black_pop_pct_chg_1940_1970": 0.006, "black_pop_pct_chg_1910_1940": 0.158, "city": "Rochester", "state": "NY", "state_fips": "36", "GISJOIN": "G36063000", "state_full": "New York", "place": "Rochester city" }, "geometry": { "type": "Point", "coordinates": [ -77.615556799638327, 43.154784500368869 ] } },
{ "type": "Feature", "properties": { "city_and_state": "Rockford, IL", "black_pop_pct_chg_1940_1970": 0.01, "black_pop_pct_chg_1910_1940": 0.069, "city": "Rockford", "state": "IL", "state_fips": "17", "GISJOIN": "G17065000", "state_full": "Illinois", "place": "Rockford city" }, "geometry": { "type": "Point", "coordinates": [ -89.093995200394829, 42.271131099992424 ] } },
{ "type": "Feature", "properties": { "city_and_state": "Roswell, NM", "black_pop_pct_chg_1940_1970": 0.008, "black_pop_pct_chg_1910_1940": 0.005, "city": "Roswell", "state": "NM", "state_fips": "35", "GISJOIN": "G35064930", "state_full": "New Mexico", "place": "Roswell city" }, "geometry": { "type": "Point", "coordinates": [ -104.523024199483018, 33.394265499793427 ] } },
{ "type": "Feature", "properties": { "city_and_state": "Rutland, VT", "black_pop_pct_chg_1940_1970": 0.001, "black_pop_pct_chg_1910_1940": 0.0, "city": "Rutland", "state": "VT", "state_fips": "50", "GISJOIN": "G50061225", "state_full": "Vermont", "place": "Rutland city" }, "geometry": { "type": "Point", "coordinates": [ -72.972606500288478, 43.610623699862522 ] } },
{ "type": "Feature", "properties": { "city_and_state": "Sacramento, CA", "black_pop_pct_chg_1940_1970": 0.003, "black_pop_pct_chg_1910_1940": 0.093, "city": "Sacramento", "state": "CA", "state_fips": "06", "GISJOIN": "G06064000", "state_full": "California", "place": "Sacramento city" }, "geometry": { "type": "Point", "coordinates": [ -121.494399600630331, 38.58157190011201 ] } },
{ "type": "Feature", "properties": { "city_and_state": "Salem, MA", "black_pop_pct_chg_1940_1970": -0.001, "black_pop_pct_chg_1910_1940": 0.002, "city": "Salem", "state": "MA", "state_fips": "25", "GISJOIN": "G25059105", "state_full": "Massachusetts", "place": "Salem city" }, "geometry": { "type": "Point", "coordinates": [ -70.896715499814277, 42.519539999717793 ] } },
{ "type": "Feature", "properties": { "city_and_state": "Salem, OR", "black_pop_pct_chg_1940_1970": -0.002, "black_pop_pct_chg_1910_1940": 0.003, "city": "Salem", "state": "OR", "state_fips": "41", "GISJOIN": "G41064900", "state_full": "Oregon", "place": "Salem city" }, "geometry": { "type": "Point", "coordinates": [ -123.035096299920312, 44.94289749980932 ] } },
{ "type": "Feature", "properties": { "city_and_state": "Salt Lake City, UT", "black_pop_pct_chg_1940_1970": -0.003, "black_pop_pct_chg_1910_1940": 0.008, "city": "Salt Lake City", "state": "UT", "state_fips": "49", "GISJOIN": "G49067000", "state_full": "Utah", "place": "Salt Lake City city" }, "geometry": { "type": "Point", "coordinates": [ -111.891047399436658, 40.760779399988635 ] } },
{ "type": "Feature", "properties": { "city_and_state": "San Antonio, TX", "black_pop_pct_chg_1940_1970": -0.035, "black_pop_pct_chg_1910_1940": 0.001, "city": "San Antonio", "state": "TX", "state_fips": "48", "GISJOIN": "G48065000", "state_full": "Texas", "place": "San Antonio city" }, "geometry": { "type": "Point", "coordinates": [ -98.49362820026316, 29.424121900054846 ] } },
{ "type": "Feature", "properties": { "city_and_state": "San Diego, CA", "black_pop_pct_chg_1940_1970": 0.005, "black_pop_pct_chg_1910_1940": 0.056, "city": "San Diego", "state": "CA", "state_fips": "06", "GISJOIN": "G06066000", "state_full": "California", "place": "San Diego city" }, "geometry": { "type": "Point", "coordinates": [ -117.157255100121418, 32.715329199896836 ] } },
{ "type": "Feature", "properties": { "city_and_state": "San Francisco, CA", "black_pop_pct_chg_1940_1970": 0.004, "black_pop_pct_chg_1910_1940": 0.127, "city": "San Francisco", "state": "CA", "state_fips": "06", "GISJOIN": "G06067000", "state_full": "California", "place": "San Francisco city" }, "geometry": { "type": "Point", "coordinates": [ -122.419415500035072, 37.774929499597334 ] } },
{ "type": "Feature", "properties": { "city_and_state": "San Jose, CA", "black_pop_pct_chg_1940_1970": -0.002, "black_pop_pct_chg_1910_1940": 0.02, "city": "San Jose", "state": "CA", "state_fips": "06", "GISJOIN": "G06068000", "state_full": "California", "place": "San Jose city" }, "geometry": { "type": "Point", "coordinates": [ -121.894955500357582, 37.339385700092812 ] } },
{ "type": "Feature", "properties": { "city_and_state": "Santa Ana, CA", "black_pop_pct_chg_1940_1970": 0.0, "black_pop_pct_chg_1910_1940": 0.038, "city": "Santa Ana", "state": "CA", "state_fips": "06", "GISJOIN": "G06069000", "state_full": "California", "place": "Santa Ana city" }, "geometry": { "type": "Point", "coordinates": [ -117.86783379988843, 33.745573100170041 ] } },
{ "type": "Feature", "properties": { "city_and_state": "Santa Fe, NM", "black_pop_pct_chg_1940_1970": -0.005, "black_pop_pct_chg_1910_1940": -0.005, "city": "Santa Fe", "state": "NM", "state_fips": "35", "GISJOIN": "G35070500", "state_full": "New Mexico", "place": "Santa Fe city" }, "geometry": { "type": "Point", "coordinates": [ -105.937799000094131, 35.686975199803001 ] } },
{ "type": "Feature", "properties": { "city_and_state": "Savannah, GA", "black_pop_pct_chg_1940_1970": -0.061, "black_pop_pct_chg_1910_1940": -0.002, "city": "Savannah", "state": "GA", "state_fips": "13", "GISJOIN": "G13069000", "state_full": "Georgia", "place": "Savannah city" }, "geometry": { "type": "Point", "coordinates": [ -81.09983420043838, 32.083540700205717 ] } },
{ "type": "Feature", "properties": { "city_and_state": "Scranton, PA", "black_pop_pct_chg_1940_1970": 0.001, "black_pop_pct_chg_1910_1940": 0.003, "city": "Scranton", "state": "PA", "state_fips": "42", "GISJOIN": "G42069000", "state_full": "Pennsylvania", "place": "Scranton city" }, "geometry": { "type": "Point", "coordinates": [ -75.662412199681015, 41.408968999904275 ] } },
{ "type": "Feature", "properties": { "city_and_state": "Seattle, WA", "black_pop_pct_chg_1940_1970": 0.001, "black_pop_pct_chg_1910_1940": 0.061, "city": "Seattle", "state": "WA", "state_fips": "53", "GISJOIN": "G53063000", "state_full": "Washington", "place": "Seattle city" }, "geometry": { "type": "Point", "coordinates": [ -122.332070799458236, 47.606209499678464 ] } },
{ "type": "Feature", "properties": { "city_and_state": "Shreveport, LA", "black_pop_pct_chg_1940_1970": -0.13, "black_pop_pct_chg_1910_1940": -0.025, "city": "Shreveport", "state": "LA", "state_fips": "22", "GISJOIN": "G22070000", "state_full": "Louisiana", "place": "Shreveport city" }, "geometry": { "type": "Point", "coordinates": [ -93.75017890021148, 32.525151599922914 ] } },
{ "type": "Feature", "properties": { "city_and_state": "Sioux City, IA", "black_pop_pct_chg_1940_1970": 0.004, "black_pop_pct_chg_1910_1940": 0.001, "city": "Sioux City", "state": "IA", "state_fips": "19", "GISJOIN": "G19073335", "state_full": "Iowa", "place": "Sioux City city" }, "geometry": { "type": "Point", "coordinates": [ -96.400306899546649, 42.499994199761048 ] } },
{ "type": "Feature", "properties": { "city_and_state": "Sioux Falls, SD", "black_pop_pct_chg_1940_1970": -0.001, "black_pop_pct_chg_1910_1940": -0.001, "city": "Sioux Falls", "state": "SD", "state_fips": "46", "GISJOIN": "G46059020", "state_full": "South Dakota", "place": "Sioux Falls city" }, "geometry": { "type": "Point", "coordinates": [ -96.700327000496543, 43.549974899752527 ] } },
{ "type": "Feature", "properties": { "city_and_state": "Somerville, MA", "black_pop_pct_chg_1940_1970": 0.0, "black_pop_pct_chg_1910_1940": 0.005, "city": "Somerville", "state": "MA", "state_fips": "25", "GISJOIN": "G25062535", "state_full": "Massachusetts", "place": "Somerville city" }, "geometry": { "type": "Point", "coordinates": [ -71.099496800406868, 42.387596799927941 ] } },
{ "type": "Feature", "properties": { "city_and_state": "South Bend, IN", "black_pop_pct_chg_1940_1970": 0.024, "black_pop_pct_chg_1910_1940": 0.106, "city": "South Bend", "state": "IN", "state_fips": "18", "GISJOIN": "G18071000", "state_full": "Indiana", "place": "South Bend city" }, "geometry": { "type": "Point", "coordinates": [ -86.250006600142001, 41.683381299936656 ] } },
{ "type": "Feature", "properties": { "city_and_state": "Sparks, NV", "black_pop_pct_chg_1940_1970": 0.002, "black_pop_pct_chg_1910_1940": 0.002, "city": "Sparks", "state": "NV", "state_fips": "32", "GISJOIN": "G32068400", "state_full": "Nevada", "place": "Sparks city" }, "geometry": { "type": "Point", "coordinates": [ -119.752688599654704, 39.534911200068358 ] } },
{ "type": "Feature", "properties": { "city_and_state": "Spokane, WA", "black_pop_pct_chg_1940_1970": -0.002, "black_pop_pct_chg_1910_1940": 0.007, "city": "Spokane", "state": "WA", "state_fips": "53", "GISJOIN": "G53067000", "state_full": "Washington", "place": "Spokane city" }, "geometry": { "type": "Point", "coordinates": [ -117.426046600134114, 47.658780300313865 ] } },
{ "type": "Feature", "properties": { "city_and_state": "Springfield, IL", "black_pop_pct_chg_1940_1970": -0.013, "black_pop_pct_chg_1910_1940": 0.037, "city": "Springfield", "state": "IL", "state_fips": "17", "GISJOIN": "G17072000", "state_full": "Illinois", "place": "Springfield city" }, "geometry": { "type": "Point", "coordinates": [ -89.643710700407368, 39.801717100382625 ] } },
{ "type": "Feature", "properties": { "city_and_state": "Springfield, MA", "black_pop_pct_chg_1940_1970": 0.004, "black_pop_pct_chg_1910_1940": 0.105, "city": "Springfield", "state": "MA", "state_fips": "25", "GISJOIN": "G25067000", "state_full": "Massachusetts", "place": "Springfield city" }, "geometry": { "type": "Point", "coordinates": [ -72.589810999971348, 42.101483100416445 ] } },
{ "type": "Feature", "properties": { "city_and_state": "Springfield, MO", "black_pop_pct_chg_1940_1970": -0.027, "black_pop_pct_chg_1910_1940": -0.01, "city": "Springfield", "state": "MO", "state_fips": "29", "GISJOIN": "G29070000", "state_full": "Missouri", "place": "Springfield city" }, "geometry": { "type": "Point", "coordinates": [ -93.298243599606735, 37.215325999734084 ] } },
{ "type": "Feature", "properties": { "city_and_state": "St. Joseph, MO", "black_pop_pct_chg_1940_1970": -0.015, "black_pop_pct_chg_1910_1940": -0.006, "city": "St. Joseph", "state": "MO", "state_fips": "29", "GISJOIN": "G29064550", "state_full": "Missouri", "place": "St. Joseph city" }, "geometry": { "type": "Point", "coordinates": [ -94.846632200159405, 39.768605499729048 ] } },
{ "type": "Feature", "properties": { "city_and_state": "St. Louis, MO", "black_pop_pct_chg_1940_1970": 0.069, "black_pop_pct_chg_1910_1940": 0.275, "city": "St. Louis", "state": "MO", "state_fips": "29", "GISJOIN": "G29065000", "state_full": "Missouri", "place": "St. Louis city" }, "geometry": { "type": "Point", "coordinates": [ -90.197888899497627, 38.627273299702345 ] } },
{ "type": "Feature", "properties": { "city_and_state": "St. Paul, MN", "black_pop_pct_chg_1940_1970": 0.0, "black_pop_pct_chg_1910_1940": 0.021, "city": "St. Paul", "state": "MN", "state_fips": "27", "GISJOIN": "G27058000", "state_full": "Minnesota", "place": "St. Paul city" }, "geometry": { "type": "Point", "coordinates": [ -93.093274200297245, 44.944410099793053 ] } },
{ "type": "Feature", "properties": { "city_and_state": "St. Petersburg, FL", "black_pop_pct_chg_1940_1970": -0.07, "black_pop_pct_chg_1910_1940": -0.049, "city": "St. Petersburg", "state": "FL", "state_fips": "12", "GISJOIN": "G12063000", "state_full": "Florida", "place": "St. Petersburg city" }, "geometry": { "type": "Point", "coordinates": [ -82.679266099995374, 27.770860600033757 ] } },
{ "type": "Feature", "properties": { "city_and_state": "Stamford, CT", "black_pop_pct_chg_1940_1970": 0.027, "black_pop_pct_chg_1910_1940": 0.084, "city": "Stamford", "state": "CT", "state_fips": "09", "GISJOIN": "G09073000", "state_full": "Connecticut", "place": "Stamford city" }, "geometry": { "type": "Point", "coordinates": [ -73.538734099476287, 41.053430200019697 ] } },
{ "type": "Feature", "properties": { "city_and_state": "Stockton, CA", "black_pop_pct_chg_1940_1970": 0.008, "black_pop_pct_chg_1910_1940": 0.094, "city": "Stockton", "state": "CA", "state_fips": "06", "GISJOIN": "G06075000", "state_full": "California", "place": "Stockton city" }, "geometry": { "type": "Point", "coordinates": [ -121.290779600087205, 37.957701599726136 ] } },
{ "type": "Feature", "properties": { "city_and_state": "Syracuse, NY", "black_pop_pct_chg_1940_1970": 0.002, "black_pop_pct_chg_1910_1940": 0.098, "city": "Syracuse", "state": "NY", "state_fips": "36", "GISJOIN": "G36073000", "state_full": "New York", "place": "Syracuse city" }, "geometry": { "type": "Point", "coordinates": [ -76.147424400013591, 43.048122099775377 ] } },
{ "type": "Feature", "properties": { "city_and_state": "Tacoma, WA", "black_pop_pct_chg_1940_1970": -0.003, "black_pop_pct_chg_1910_1940": 0.062, "city": "Tacoma", "state": "WA", "state_fips": "53", "GISJOIN": "G53070000", "state_full": "Washington", "place": "Tacoma city" }, "geometry": { "type": "Point", "coordinates": [ -122.444290600322049, 47.25287689991967 ] } },
{ "type": "Feature", "properties": { "city_and_state": "Tallahassee, FL", "black_pop_pct_chg_1940_1970": -0.246, "black_pop_pct_chg_1910_1940": -0.146, "city": "Tallahassee", "state": "FL", "state_fips": "12", "GISJOIN": "G12070600", "state_full": "Florida", "place": "Tallahassee city" }, "geometry": { "type": "Point", "coordinates": [ -84.280732900160203, 30.438255900106991 ] } },
{ "type": "Feature", "properties": { "city_and_state": "Tampa, FL", "black_pop_pct_chg_1940_1970": -0.022, "black_pop_pct_chg_1910_1940": -0.018, "city": "Tampa", "state": "FL", "state_fips": "12", "GISJOIN": "G12071000", "state_full": "Florida", "place": "Tampa city" }, "geometry": { "type": "Point", "coordinates": [ -82.458427900193954, 27.94752160042977 ] } },
{ "type": "Feature", "properties": { "city_and_state": "Tempe, AZ", "black_pop_pct_chg_1940_1970": null, "black_pop_pct_chg_1910_1940": 0.007, "city": "Tempe", "state": "AZ", "state_fips": "04", "GISJOIN": "G04073000", "state_full": "Arizona", "place": "Tempe city" }, "geometry": { "type": "Point", "coordinates": [ -111.909309500445502, 33.414767999593757 ] } },
{ "type": "Feature", "properties": { "city_and_state": "Toledo, OH", "black_pop_pct_chg_1940_1970": 0.041, "black_pop_pct_chg_1910_1940": 0.086, "city": "Toledo", "state": "OH", "state_fips": "39", "GISJOIN": "G39077000", "state_full": "Ohio", "place": "Toledo city" }, "geometry": { "type": "Point", "coordinates": [ -83.555212000589279, 41.663938299994463 ] } },
{ "type": "Feature", "properties": { "city_and_state": "Topeka, KS", "black_pop_pct_chg_1940_1970": -0.02, "black_pop_pct_chg_1910_1940": 0.0, "city": "Topeka", "state": "KS", "state_fips": "20", "GISJOIN": "G20071000", "state_full": "Kansas", "place": "Topeka city" }, "geometry": { "type": "Point", "coordinates": [ -95.678037100041109, 39.048333600011709 ] } },
{ "type": "Feature", "properties": { "city_and_state": "Trenton, NJ", "black_pop_pct_chg_1940_1970": 0.048, "black_pop_pct_chg_1910_1940": 0.304, "city": "Trenton", "state": "NJ", "state_fips": "34", "GISJOIN": "G34074000", "state_full": "New Jersey", "place": "Trenton city" }, "geometry": { "type": "Point", "coordinates": [ -74.742938499609693, 40.217053400261221 ] } },
{ "type": "Feature", "properties": { "city_and_state": "Tucson, AZ", "black_pop_pct_chg_1940_1970": 0.029, "black_pop_pct_chg_1910_1940": -0.011, "city": "Tucson", "state": "AZ", "state_fips": "04", "GISJOIN": "G04077000", "state_full": "Arizona", "place": "Tucson city" }, "geometry": { "type": "Point", "coordinates": [ -110.926478999637027, 32.22174289981097 ] } },
{ "type": "Feature", "properties": { "city_and_state": "Tulsa, OK", "black_pop_pct_chg_1940_1970": -0.001, "black_pop_pct_chg_1910_1940": 0.0, "city": "Tulsa", "state": "OK", "state_fips": "40", "GISJOIN": "G40075000", "state_full": "Oklahoma", "place": "Tulsa city" }, "geometry": { "type": "Point", "coordinates": [ -95.992775000213868, 36.153981599675383 ] } },
{ "type": "Feature", "properties": { "city_and_state": "Utica, NY", "black_pop_pct_chg_1940_1970": 0.0, "black_pop_pct_chg_1910_1940": 0.051, "city": "Utica", "state": "NY", "state_fips": "36", "GISJOIN": "G36076540", "state_full": "New York", "place": "Utica city" }, "geometry": { "type": "Point", "coordinates": [ -75.232664099960616, 43.100903099780844 ] } },
{ "type": "Feature", "properties": { "city_and_state": "Vicksburg, MS", "black_pop_pct_chg_1940_1970": -0.067, "black_pop_pct_chg_1910_1940": -0.018, "city": "Vicksburg", "state": "MS", "state_fips": "28", "GISJOIN": "G28076720", "state_full": "Mississippi", "place": "Vicksburg city" }, "geometry": { "type": "Point", "coordinates": [ -90.877882100304788, 32.352645700353598 ] } },
{ "type": "Feature", "properties": { "city_and_state": "Waco, TX", "black_pop_pct_chg_1940_1970": -0.033, "black_pop_pct_chg_1910_1940": 0.002, "city": "Waco", "state": "TX", "state_fips": "48", "GISJOIN": "G48076000", "state_full": "Texas", "place": "Waco city" }, "geometry": { "type": "Point", "coordinates": [ -97.146669500042876, 31.549332999720015 ] } },
{ "type": "Feature", "properties": { "city_and_state": "Warwick, RI", "black_pop_pct_chg_1940_1970": 0.001, "black_pop_pct_chg_1910_1940": -0.004, "city": "Warwick", "state": "RI", "state_fips": "44", "GISJOIN": "G44074300", "state_full": "Rhode Island", "place": "Warwick city" }, "geometry": { "type": "Point", "coordinates": [ -71.416167099404305, 41.700101000262038 ] } },
{ "type": "Feature", "properties": { "city_and_state": "Washington, DC", "black_pop_pct_chg_1940_1970": -0.003, "black_pop_pct_chg_1910_1940": 0.428, "city": "Washington", "state": "DC", "state_fips": "11", "GISJOIN": "G11050000", "state_full": "District Of Columbia", "place": "Washington city" }, "geometry": { "type": "Point", "coordinates": [ -77.036365800232915, 38.895111800073643 ] } },
{ "type": "Feature", "properties": { "city_and_state": "Waterbury, CT", "black_pop_pct_chg_1940_1970": 0.01, "black_pop_pct_chg_1910_1940": 0.081, "city": "Waterbury", "state": "CT", "state_fips": "09", "GISJOIN": "G09080000", "state_full": "Connecticut", "place": "Waterbury city" }, "geometry": { "type": "Point", "coordinates": [ -73.051496600440672, 41.558152500079608 ] } },
{ "type": "Feature", "properties": { "city_and_state": "Wheeling, WV", "black_pop_pct_chg_1940_1970": 0.002, "black_pop_pct_chg_1910_1940": 0.006, "city": "Wheeling", "state": "WV", "state_fips": "54", "GISJOIN": "G54086452", "state_full": "West Virginia", "place": "Wheeling city" }, "geometry": { "type": "Point", "coordinates": [ -80.720914900427275, 40.063961599990705 ] } },
{ "type": "Feature", "properties": { "city_and_state": "Wichita Falls, TX", "black_pop_pct_chg_1940_1970": 0.019, "black_pop_pct_chg_1910_1940": 0.005, "city": "Wichita Falls", "state": "TX", "state_fips": "48", "GISJOIN": "G48079000", "state_full": "Texas", "place": "Wichita Falls city" }, "geometry": { "type": "Point", "coordinates": [ -98.493387299657158, 33.913708499739471 ] } },
{ "type": "Feature", "properties": { "city_and_state": "Wichita, KS", "black_pop_pct_chg_1940_1970": 0.003, "black_pop_pct_chg_1910_1940": 0.048, "city": "Wichita", "state": "KS", "state_fips": "20", "GISJOIN": "G20079000", "state_full": "Kansas", "place": "Wichita city" }, "geometry": { "type": "Point", "coordinates": [ -97.337544799806864, 37.692236100219752 ] } },
{ "type": "Feature", "properties": { "city_and_state": "Wilmington, DE", "black_pop_pct_chg_1940_1970": 0.023, "black_pop_pct_chg_1910_1940": 0.31, "city": "Wilmington", "state": "DE", "state_fips": "10", "GISJOIN": "G10077580", "state_full": "Delaware", "place": "Wilmington city" }, "geometry": { "type": "Point", "coordinates": [ -75.546588899694427, 39.745946699576479 ] } },
{ "type": "Feature", "properties": { "city_and_state": "Wilmington, NC", "black_pop_pct_chg_1940_1970": -0.066, "black_pop_pct_chg_1910_1940": -0.061, "city": "Wilmington", "state": "NC", "state_fips": "37", "GISJOIN": "G37074440", "state_full": "North Carolina", "place": "Wilmington city" }, "geometry": { "type": "Point", "coordinates": [ -77.944710199730139, 34.225725600183388 ] } },
{ "type": "Feature", "properties": { "city_and_state": "Winston-Salem, NC", "black_pop_pct_chg_1940_1970": 0.051, "black_pop_pct_chg_1910_1940": -0.109, "city": "Winston-Salem", "state": "NC", "state_fips": "37", "GISJOIN": "G37075000", "state_full": "North Carolina", "place": "Winston-Salem city" }, "geometry": { "type": "Point", "coordinates": [ -80.244215999744682, 36.099859599875323 ] } },
{ "type": "Feature", "properties": { "city_and_state": "Woonsocket, RI", "black_pop_pct_chg_1940_1970": 0.001, "black_pop_pct_chg_1910_1940": 0.012, "city": "Woonsocket", "state": "RI", "state_fips": "44", "GISJOIN": "G44080780", "state_full": "Rhode Island", "place": "Woonsocket city" }, "geometry": { "type": "Point", "coordinates": [ -71.51478389935258, 42.002876100269667 ] } },
{ "type": "Feature", "properties": { "city_and_state": "Worcester, MA", "black_pop_pct_chg_1940_1970": -0.002, "black_pop_pct_chg_1910_1940": 0.012, "city": "Worcester", "state": "MA", "state_fips": "25", "GISJOIN": "G25082000", "state_full": "Massachusetts", "place": "Worcester city" }, "geometry": { "type": "Point", "coordinates": [ -71.802293400447113, 42.262593200191972 ] } },
{ "type": "Feature", "properties": { "city_and_state": "Yonkers, NY", "black_pop_pct_chg_1940_1970": 0.009, "black_pop_pct_chg_1910_1940": 0.035, "city": "Yonkers", "state": "NY", "state_fips": "36", "GISJOIN": "G36084000", "state_full": "New York", "place": "Yonkers city" }, "geometry": { "type": "Point", "coordinates": [ -73.898746900055059, 40.931209899631234 ] } },
{ "type": "Feature", "properties": { "city_and_state": "Youngstown, OH", "black_pop_pct_chg_1940_1970": 0.063, "black_pop_pct_chg_1910_1940": 0.165, "city": "Youngstown", "state": "OH", "state_fips": "39", "GISJOIN": "G39088000", "state_full": "Ohio", "place": "Youngstown city" }, "geometry": { "type": "Point", "coordinates": [ -80.64951939987759, 41.099780300427383 ] } }
]
}
